{"success":true,"errorCode":1000000,"errorMsg":null,"result":{"extraInfoVO":{"pid":null,"listId":"1595234016163_7c1ff499a857b788c322b7a1292e8346","searchId":"171874b69c5fd42f9998b7ca18d56eb6bd4"},"isWhiteList":null,"isEnoughOrder":null,"total":5123,"goodsList":[{"mallId":9212563,"mallName":"AFLCOLE家居旗舰店","mallLogo":null,"qrCodeImageUrl":null,"merchantType":3,"hasCltCpn":false,"goodsId":68299694615,"goodsName":"【驱蚊洗衣液】婴儿洗衣液皂液婴幼儿童宝宝专用去渍抑菌 500Ml","goodsDesc":"【驱蚊洗衣液】婴儿洗衣液皂液婴幼儿童宝宝专用去渍抑菌 500Ml","goodsImageUrl":"https://t00img.yangkeduo.com/goods/images/2020-07-11/8da240e9124834fc4ea90163f03715ea.jpeg","goodsThumbnailUrl":"https://t00img.yangkeduo.com/goods/images/2020-07-11/8da240e9124834fc4ea90163f03715ea.jpeg","minGroupPrice":4990,"categoryId":10110,"categoryName":"洗护","goodsType":1,"hasPddCoupon":null,"hasCoupon":true,"couponMinOrderAmount":2000,"couponDiscount":2000,"couponTotalQuantity":2000,"couponRemainQuantity":1300,"couponStartTime":1595088000,"couponEndTime":1595433599,"mallClientAble":true,"planType":4,"zsDuoId":9748310,"planTypeAll":4,"promotionRate":200,"mallRate":50,"optId":10110,"collected":false,"salesTip":"3689","descTxt":"高","servTxt":"高","lgstTxt":"高","isSceneAuth":true,"inBigSale":[10037,10078,10044,10098,10064],"haohuoCouponList":null,"timingUnitVO":null,"brandCouponList":[],"isOnsale":true,"isExtraMissionGoods":false,"unifiedTag":{"tagDTOs":[{"tagSeries":1,"tagId":3,"text":"退货包运费","color":"#FF5706","url":null}],"iconDTOs":[]},"matchType":0},{"mallId":997746,"mallName":"恩涵日用百货","mallLogo":null,"qrCodeImageUrl":null,"merchantType":1,"hasCltCpn":false,"goodsId":146642392418,"goodsName":"搓澡巾女神器强力去污澡巾成人搓澡后背不求人搓背洗澡巾拉背条","goodsDesc":"搓澡巾女神器强力去污澡巾成人搓澡后背不求人搓背洗澡巾拉背条","goodsImageUrl":"https://t00img.yangkeduo.com/goods/images/2020-07-04/bac7349940093b9ff6bd47c0745aaeaa.jpeg","goodsThumbnailUrl":"https://t00img.yangkeduo.com/goods/images/2020-07-04/bac7349940093b9ff6bd47c0745aaeaa.jpeg","minGroupPrice":3500,"categoryId":10110,"categoryName":"洗护","goodsType":1,"hasPddCoupon":null,"hasCoupon":true,"couponMinOrderAmount":2000,"couponDiscount":2000,"couponTotalQuantity":10000,"couponRemainQuantity":6100,"couponStartTime":1595088000,"couponEndTime":1595692799,"mallClientAble":true,"planType":4,"zsDuoId":1001021,"planTypeAll":4,"promotionRate":200,"mallRate":50,"optId":10110,"collected":false,"salesTip":"8883","descTxt":"高","servTxt":"高","lgstTxt":"高","isSceneAuth":false,"inBigSale":[10044,10289,10078,21,10097,10000,10098,10037],"haohuoCouponList":null,"timingUnitVO":null,"brandCouponList":[],"isOnsale":true,"isExtraMissionGoods":false,"unifiedTag":{"tagDTOs":[{"tagSeries":1,"tagId":3,"text":"退货包运费","color":"#FF5706","url":null}],"iconDTOs":[]},"matchType":0},{"mallId":929084256,"mallName":"涂牛家居生活专营店","mallLogo":null,"qrCodeImageUrl":null,"merchantType":5,"hasCltCpn":false,"goodsId":125371473892,"goodsName":"洁厕剂洁厕液除菌除臭厕所除臭马桶清洁剂洁厕灵卫生间清新实惠装","goodsDesc":"洁厕剂洁厕液除菌除臭厕所除臭马桶清洁剂洁厕灵卫生间清新实惠装","goodsImageUrl":"https://t00img.yangkeduo.com/goods/images/2020-07-13/57986de2df7ff4b87251164fad80ec61.jpeg","goodsThumbnailUrl":"https://t00img.yangkeduo.com/goods/images/2020-07-13/57986de2df7ff4b87251164fad80ec61.jpeg","minGroupPrice":5800,"categoryId":10110,"categoryName":"洗护","goodsType":1,"hasPddCoupon":null,"hasCoupon":true,"couponMinOrderAmount":2000,"couponDiscount":2000,"couponTotalQuantity":5000,"couponRemainQuantity":4600,"couponStartTime":1595088000,"couponEndTime":1595347199,"mallClientAble":true,"planType":4,"zsDuoId":8360828,"planTypeAll":4,"promotionRate":200,"mallRate":10,"optId":10110,"collected":false,"salesTip":"2万","descTxt":"高","servTxt":"高","lgstTxt":"高","isSceneAuth":true,"inBigSale":[10064,10078,10037,10098,10289,10097,10044],"haohuoCouponList":null,"timingUnitVO":null,"brandCouponList":[],"isOnsale":true,"isExtraMissionGoods":false,"unifiedTag":null,"matchType":0},{"mallId":869799108,"mallName":"逸九天官方旗舰店","mallLogo":null,"qrCodeImageUrl":null,"merchantType":3,"hasCltCpn":false,"goodsId":50199457361,"goodsName":"塑料袋白色食品袋外卖打包方便袋大小号背心手提袋一次性透明袋子","goodsDesc":"塑料袋白色食品袋外卖打包方便袋大小号背心手提袋一次性透明袋子","goodsImageUrl":"https://t00img.yangkeduo.com/goods/images/images/2019-10-05/3d476f7e03078c8a9b63f8e037ba1ab9.jpeg","goodsThumbnailUrl":"https://t00img.yangkeduo.com/goods/images/images/2019-10-05/3d476f7e03078c8a9b63f8e037ba1ab9.jpeg","minGroupPrice":4590,"categoryId":20527,"categoryName":"百货","goodsType":1,"hasPddCoupon":null,"hasCoupon":true,"couponMinOrderAmount":3000,"couponDiscount":3000,"couponTotalQuantity":10000,"couponRemainQuantity":6000,"couponStartTime":1594828800,"couponEndTime":1595260799,"mallClientAble":true,"planType":4,"zsDuoId":9869006,"planTypeAll":4,"promotionRate":200,"mallRate":1,"optId":20527,"collected":false,"salesTip":"7.2万","descTxt":"高","servTxt":"高","lgstTxt":"高","isSceneAuth":true,"inBigSale":[10311,10294,10289,10064,10044,10277,10097,10298,10037,10098,10078,10000,10296,21],"haohuoCouponList":null,"timingUnitVO":null,"brandCouponList":[],"isOnsale":true,"isExtraMissionGoods":false,"unifiedTag":{"tagDTOs":[{"tagSeries":1,"tagId":3,"text":"退货包运费","color":"#FF5706","url":null},{"tagSeries":1,"tagId":24,"text":"极速退款","color":"#FF5706","url":null}],"iconDTOs":[{"tagSeries":2,"tagId":20013,"text":null,"color":"","url":"https://commimg.pddpic.com/oms_img_ng/2020-07-06/b763cbc5-a35d-4102-a57c-eaaba441c7b8.png"}]},"matchType":0},{"mallId":298607134,"mallName":"萱儿兰服饰专营店","mallLogo":null,"qrCodeImageUrl":null,"merchantType":5,"hasCltCpn":false,"goodsId":149558473597,"goodsName":"七分/九分2020新款运动裤女春夏薄款大码女装宽松显瘦休闲哈伦裤","goodsDesc":"七分/九分2020新款运动裤女春夏薄款大码女装宽松显瘦休闲哈伦裤","goodsImageUrl":"https://t00img.yangkeduo.com/goods/images/2020-07-08/aef9c262d03c75701aecd34a8608941d.jpeg","goodsThumbnailUrl":"https://t00img.yangkeduo.com/goods/images/2020-07-08/aef9c262d03c75701aecd34a8608941d.jpeg","minGroupPrice":10900,"categoryId":17370,"categoryName":"女装","goodsType":1,"hasPddCoupon":null,"hasCoupon":true,"couponMinOrderAmount":4000,"couponDiscount":4000,"couponTotalQuantity":5000,"couponRemainQuantity":2300,"couponStartTime":1595088000,"couponEndTime":1595260799,"mallClientAble":false,"planType":4,"zsDuoId":9051343,"planTypeAll":4,"promotionRate":200,"mallRate":10,"optId":17370,"collected":false,"salesTip":"6413","descTxt":"高","servTxt":"高","lgstTxt":"高","isSceneAuth":false,"inBigSale":[10289,10098,10078,10037,10044,10097],"haohuoCouponList":null,"timingUnitVO":null,"brandCouponList":[],"isOnsale":true,"isExtraMissionGoods":false,"unifiedTag":{"tagDTOs":[{"tagSeries":1,"tagId":3,"text":"退货包运费","color":"#FF5706","url":null}],"iconDTOs":[]},"matchType":0},{"mallId":864068,"mallName":"孟智生态果园","mallLogo":null,"qrCodeImageUrl":null,"merchantType":1,"hasCltCpn":false,"goodsId":154445099731,"goodsName":"真贝贝南瓜日本进口种源小南瓜栗面迷你宝宝辅食新鲜蔬菜包邮","goodsDesc":"真贝贝南瓜日本进口种源小南瓜栗面迷你宝宝辅食新鲜蔬菜包邮","goodsImageUrl":"https://t00img.yangkeduo.com/goods/images/2020-07-18/590d61ebe98039329bb8fcd28b0042d5.jpeg","goodsThumbnailUrl":"https://t00img.yangkeduo.com/goods/images/2020-07-18/590d61ebe98039329bb8fcd28b0042d5.jpeg","minGroupPrice":15900,"categoryId":10696,"categoryName":"海淘","goodsType":1,"hasPddCoupon":null,"hasCoupon":true,"couponMinOrderAmount":8000,"couponDiscount":8000,"couponTotalQuantity":10000,"couponRemainQuantity":6100,"couponStartTime":1595001600,"couponEndTime":1595347199,"mallClientAble":true,"planType":4,"zsDuoId":1972641,"planTypeAll":4,"promotionRate":200,"mallRate":10,"optId":10696,"collected":false,"salesTip":"802","descTxt":"高","servTxt":"高","lgstTxt":"高","isSceneAuth":true,"inBigSale":[10078,10037,10098],"haohuoCouponList":null,"timingUnitVO":null,"brandCouponList":[],"isOnsale":true,"isExtraMissionGoods":false,"unifiedTag":null,"matchType":0},{"mallId":56880,"mallName":"纤诗洁家居旗舰店","mallLogo":null,"qrCodeImageUrl":null,"merchantType":3,"hasCltCpn":false,"goodsId":138641551897,"goodsName":"超强吸水速干干发帽女洗头发速干的毛巾包头洗澡浴巾帽抖音同款","goodsDesc":"超强吸水速干干发帽女洗头发速干的毛巾包头洗澡浴巾帽抖音同款","goodsImageUrl":"https://t00img.yangkeduo.com/goods/images/2020-06-23/b2e4d861262eb4c214165230f5a81d3f.jpeg","goodsThumbnailUrl":"https://t00img.yangkeduo.com/goods/images/2020-06-23/b2e4d861262eb4c214165230f5a81d3f.jpeg","minGroupPrice":4990,"categoryId":10110,"categoryName":"洗护","goodsType":1,"hasPddCoupon":null,"hasCoupon":true,"couponMinOrderAmount":2000,"couponDiscount":2000,"couponTotalQuantity":4000,"couponRemainQuantity":2900,"couponStartTime":1595174400,"couponEndTime":1595606399,"mallClientAble":true,"planType":4,"zsDuoId":2001639,"planTypeAll":4,"promotionRate":200,"mallRate":10,"optId":10110,"collected":false,"salesTip":"3.1万","descTxt":"高","servTxt":"高","lgstTxt":"高","isSceneAuth":true,"inBigSale":[10000,10098,10289,10037,10097,21,10078,10044],"haohuoCouponList":null,"timingUnitVO":null,"brandCouponList":[],"isOnsale":true,"isExtraMissionGoods":false,"unifiedTag":{"tagDTOs":[{"tagSeries":1,"tagId":3,"text":"退货包运费","color":"#FF5706","url":null},{"tagSeries":1,"tagId":24,"text":"极速退款","color":"#FF5706","url":null}],"iconDTOs":[]},"matchType":0},{"mallId":221204083,"mallName":"YOUJIA优家人家居生活店","mallLogo":null,"qrCodeImageUrl":null,"merchantType":1,"hasCltCpn":false,"goodsId":152867245527,"goodsName":"装衣服被子的袋子棉被收纳袋大号衣物打包袋整理袋手提行李包搬家","goodsDesc":"装衣服被子的袋子棉被收纳袋大号衣物打包袋整理袋手提行李包搬家","goodsImageUrl":"https://t00img.yangkeduo.com/goods/images/2020-07-15/295060484da8a243d45d31527f2205b6.jpeg","goodsThumbnailUrl":"https://t00img.yangkeduo.com/goods/images/2020-07-15/295060484da8a243d45d31527f2205b6.jpeg","minGroupPrice":8800,"categoryId":11463,"categoryName":"收纳整理","goodsType":1,"hasPddCoupon":null,"hasCoupon":true,"couponMinOrderAmount":1000,"couponDiscount":1000,"couponTotalQuantity":2000,"couponRemainQuantity":1700,"couponStartTime":1595174400,"couponEndTime":1596211199,"mallClientAble":true,"planType":4,"zsDuoId":8589953,"planTypeAll":5,"promotionRate":200,"mallRate":100,"optId":11463,"collected":false,"salesTip":"587","descTxt":"高","servTxt":"高","lgstTxt":"高","isSceneAuth":false,"inBigSale":[10078,10098],"haohuoCouponList":null,"timingUnitVO":null,"brandCouponList":[],"isOnsale":true,"isExtraMissionGoods":false,"unifiedTag":{"tagDTOs":[{"tagSeries":1,"tagId":3,"text":"退货包运费","color":"#FF5706","url":null},{"tagSeries":1,"tagId":24,"text":"极速退款","color":"#FF5706","url":null}],"iconDTOs":[]},"matchType":0},{"mallId":258737566,"mallName":"百万家居生活专营店","mallLogo":null,"qrCodeImageUrl":null,"merchantType":5,"hasCltCpn":false,"goodsId":150101105873,"goodsName":"彩漂粉全能型污渍彩色衣服漂白剂家用万能儿童抖音同款去黄彩漂剂","goodsDesc":"彩漂粉全能型污渍彩色衣服漂白剂家用万能儿童抖音同款去黄彩漂剂","goodsImageUrl":"https://t00img.yangkeduo.com/goods/images/2020-07-10/ae406807a6c2ad268bfcbce15b57dcb0.jpeg","goodsThumbnailUrl":"https://t00img.yangkeduo.com/goods/images/2020-07-10/ae406807a6c2ad268bfcbce15b57dcb0.jpeg","minGroupPrice":5900,"categoryId":10110,"categoryName":"洗护","goodsType":1,"hasPddCoupon":null,"hasCoupon":true,"couponMinOrderAmount":2000,"couponDiscount":2000,"couponTotalQuantity":2000,"couponRemainQuantity":1600,"couponStartTime":1595174400,"couponEndTime":1595347199,"mallClientAble":true,"planType":4,"zsDuoId":8638825,"planTypeAll":4,"promotionRate":200,"mallRate":10,"optId":10110,"collected":false,"salesTip":"9418","descTxt":"高","servTxt":"高","lgstTxt":"高","isSceneAuth":true,"inBigSale":[10037,10078,10097,10044,10098],"haohuoCouponList":null,"timingUnitVO":null,"brandCouponList":[],"isOnsale":true,"isExtraMissionGoods":false,"unifiedTag":{"tagDTOs":[{"tagSeries":1,"tagId":3,"text":"退货包运费","color":"#FF5706","url":null},{"tagSeries":1,"tagId":24,"text":"极速退款","color":"#FF5706","url":null}],"iconDTOs":[]},"matchType":0},{"mallId":911453498,"mallName":"比波比美妆专营店","mallLogo":null,"qrCodeImageUrl":null,"merchantType":5,"hasCltCpn":true,"goodsId":148125964682,"goodsName":"【超级显白】免烤不可撕持久防水无毒显白夏季裸粉新款脚趾指甲油","goodsDesc":"【超级显白】免烤不可撕持久防水无毒显白夏季裸粉新款脚趾指甲油","goodsImageUrl":"https://t00img.yangkeduo.com/goods/images/2020-07-13/939d9d7918c7df955107a78e1615a621.jpeg","goodsThumbnailUrl":"https://t00img.yangkeduo.com/goods/images/2020-07-13/939d9d7918c7df955107a78e1615a621.jpeg","minGroupPrice":6900,"categoryId":12,"categoryName":"海淘","goodsType":1,"hasPddCoupon":null,"hasCoupon":true,"couponMinOrderAmount":3000,"couponDiscount":3000,"couponTotalQuantity":1000,"couponRemainQuantity":550,"couponStartTime":1595174400,"couponEndTime":1595347199,"mallClientAble":true,"planType":4,"zsDuoId":9539749,"planTypeAll":4,"promotionRate":200,"mallRate":10,"optId":12,"collected":false,"salesTip":"4462","descTxt":"高","servTxt":"高","lgstTxt":"高","isSceneAuth":true,"inBigSale":[10037,10097,10078,10289,10098,10044],"haohuoCouponList":null,"timingUnitVO":null,"brandCouponList":[],"isOnsale":true,"isExtraMissionGoods":false,"unifiedTag":null,"matchType":0},{"mallId":337972805,"mallName":"御茶园茶店","mallLogo":null,"qrCodeImageUrl":null,"merchantType":1,"hasCltCpn":false,"goodsId":143706268794,"goodsName":"茶叶铁观音茶叶浓香特级正宗安溪新茶传统工艺2020清香兰花香散装","goodsDesc":"茶叶铁观音茶叶浓香特级正宗安溪新茶传统工艺2020清香兰花香散装","goodsImageUrl":"https://t00img.yangkeduo.com/goods/images/2020-06-29/3d6dc38fee7f6059f7df9c3b3aabdcdb.jpeg","goodsThumbnailUrl":"https://t00img.yangkeduo.com/goods/images/2020-06-29/3d6dc38fee7f6059f7df9c3b3aabdcdb.jpeg","minGroupPrice":8900,"categoryId":11906,"categoryName":"茶","goodsType":1,"hasPddCoupon":null,"hasCoupon":true,"couponMinOrderAmount":3000,"couponDiscount":3000,"couponTotalQuantity":3000,"couponRemainQuantity":2600,"couponStartTime":1595174400,"couponEndTime":1595433599,"mallClientAble":true,"planType":4,"zsDuoId":9345379,"planTypeAll":4,"promotionRate":200,"mallRate":200,"optId":11906,"collected":false,"salesTip":"3256","descTxt":"高","servTxt":"高","lgstTxt":"高","isSceneAuth":true,"inBigSale":[10078,10098,10044,10037],"haohuoCouponList":null,"timingUnitVO":null,"brandCouponList":[],"isOnsale":true,"isExtraMissionGoods":false,"unifiedTag":{"tagDTOs":[{"tagSeries":1,"tagId":3,"text":"退货包运费","color":"#FF5706","url":null},{"tagSeries":1,"tagId":24,"text":"极速退款","color":"#FF5706","url":null}],"iconDTOs":[]},"matchType":0},{"mallId":235016265,"mallName":"珍正美食品专营店","mallLogo":null,"qrCodeImageUrl":null,"merchantType":5,"hasCltCpn":false,"goodsId":106177461853,"goodsName":"三五火锅底料全新重庆火锅料四川麻辣烫串串调料老火锅底料150g","goodsDesc":"三五火锅底料全新重庆火锅料四川麻辣烫串串调料老火锅底料150g,[生产日期2020年1月10日】【保质期18个月】","goodsImageUrl":"https://t00img.yangkeduo.com/goods/images/2020-05-10/ed5ae2550b44334b2036d7f4f4d62122.jpeg","goodsThumbnailUrl":"https://t00img.yangkeduo.com/goods/images/2020-05-10/ed5ae2550b44334b2036d7f4f4d62122.jpeg","minGroupPrice":7900,"categoryId":1,"categoryName":"食品","goodsType":1,"hasPddCoupon":null,"hasCoupon":true,"couponMinOrderAmount":5000,"couponDiscount":5000,"couponTotalQuantity":4000,"couponRemainQuantity":1200,"couponStartTime":1595088000,"couponEndTime":1595779199,"mallClientAble":true,"planType":4,"zsDuoId":8576180,"planTypeAll":4,"promotionRate":200,"mallRate":10,"optId":1,"collected":false,"salesTip":"1.6万","descTxt":"高","servTxt":"高","lgstTxt":"高","isSceneAuth":true,"inBigSale":[10289,10098,10097,21,10044,10037,10064,10000,10078],"haohuoCouponList":null,"timingUnitVO":null,"brandCouponList":[],"isOnsale":true,"isExtraMissionGoods":false,"unifiedTag":{"tagDTOs":[{"tagSeries":1,"tagId":3,"text":"退货包运费","color":"#FF5706","url":null},{"tagSeries":1,"tagId":24,"text":"极速退款","color":"#FF5706","url":null}],"iconDTOs":[]},"matchType":0},{"mallId":387432215,"mallName":"林济精选食品店","mallLogo":null,"qrCodeImageUrl":null,"merchantType":6,"hasCltCpn":false,"goodsId":89562618069,"goodsName":"林济益生元羊奶贝内蒙古特产牛奶干吃奶片糖高钙休闲零食现货包邮","goodsDesc":"林济益生元羊奶贝内蒙古特产牛奶干吃奶片糖高钙休闲零食现货包邮","goodsImageUrl":"https://t00img.yangkeduo.com/goods/images/2020-03-08/24441dc0b17ad1136ea6a0ee7f0c329c.jpeg","goodsThumbnailUrl":"https://t00img.yangkeduo.com/goods/images/2020-03-08/24441dc0b17ad1136ea6a0ee7f0c329c.jpeg","minGroupPrice":12900,"categoryId":1,"categoryName":"食品","goodsType":1,"hasPddCoupon":null,"hasCoupon":true,"couponMinOrderAmount":9000,"couponDiscount":9000,"couponTotalQuantity":3000,"couponRemainQuantity":2600,"couponStartTime":1595174400,"couponEndTime":1595433599,"mallClientAble":true,"planType":4,"zsDuoId":10630603,"planTypeAll":4,"promotionRate":300,"mallRate":10,"optId":1,"collected":false,"salesTip":"3842","descTxt":"高","servTxt":"高","lgstTxt":"高","isSceneAuth":true,"inBigSale":[10064,10078,10000,10044,10142,10098,10037],"haohuoCouponList":null,"timingUnitVO":null,"brandCouponList":[],"isOnsale":true,"isExtraMissionGoods":false,"unifiedTag":{"tagDTOs":[{"tagSeries":1,"tagId":3,"text":"退货包运费","color":"#FF5706","url":null},{"tagSeries":1,"tagId":24,"text":"极速退款","color":"#FF5706","url":null}],"iconDTOs":[]},"matchType":0},{"mallId":648114599,"mallName":"优良集","mallLogo":null,"qrCodeImageUrl":null,"merchantType":1,"hasCltCpn":false,"goodsId":122253375932,"goodsName":"鸣兴蛋黄酥网红雪媚娘手工正品咸蛋糯米糕点月饼零食早餐馈赠佳品","goodsDesc":"鸣兴蛋黄酥网红雪媚娘手工正品咸蛋糯米糕点月饼零食早餐馈赠佳品","goodsImageUrl":"https://t00img.yangkeduo.com/goods/images/2020-05-15/3d9523cf9f476be8efadf89050eee9ee.jpeg","goodsThumbnailUrl":"https://t00img.yangkeduo.com/goods/images/2020-05-15/3d9523cf9f476be8efadf89050eee9ee.jpeg","minGroupPrice":7880,"categoryId":1,"categoryName":"食品","goodsType":1,"hasPddCoupon":null,"hasCoupon":true,"couponMinOrderAmount":5000,"couponDiscount":5000,"couponTotalQuantity":3000,"couponRemainQuantity":1400,"couponStartTime":1595088000,"couponEndTime":1595779199,"mallClientAble":false,"planType":4,"zsDuoId":10652652,"planTypeAll":4,"promotionRate":200,"mallRate":50,"optId":1,"collected":false,"salesTip":"2256","descTxt":"高","servTxt":"高","lgstTxt":"高","isSceneAuth":false,"inBigSale":[10114,10138,10078,10277,10127,10304,10142,10096,10098,10044,10311,10289,10294,10286,10296,10140,10306],"haohuoCouponList":null,"timingUnitVO":null,"brandCouponList":[],"isOnsale":true,"isExtraMissionGoods":false,"unifiedTag":{"tagDTOs":[{"tagSeries":1,"tagId":24,"text":"极速退款","color":"#FF5706","url":null}],"iconDTOs":[{"tagSeries":2,"tagId":20013,"text":null,"color":"","url":"https://commimg.pddpic.com/oms_img_ng/2020-07-06/b763cbc5-a35d-4102-a57c-eaaba441c7b8.png"}]},"matchType":0},{"mallId":440533071,"mallName":"千米深井食品旗舰店","mallLogo":null,"qrCodeImageUrl":null,"merchantType":3,"hasCltCpn":false,"goodsId":140694702878,"goodsName":"久大千米深井食盐加碘食用盐家用调味料四川特产烧烤调料无碘食盐","goodsDesc":"久大千米深井食盐加碘食用盐家用调味料四川特产烧烤调料无碘食盐","goodsImageUrl":"https://t00img.yangkeduo.com/goods/images/2020-07-20/5c0408796193b13c67e214b3ca7c4b83.jpeg","goodsThumbnailUrl":"https://t00img.yangkeduo.com/goods/images/2020-07-20/5c0408796193b13c67e214b3ca7c4b83.jpeg","minGroupPrice":6900,"categoryId":1,"categoryName":"食品","goodsType":1,"hasPddCoupon":null,"hasCoupon":true,"couponMinOrderAmount":4000,"couponDiscount":4000,"couponTotalQuantity":10000,"couponRemainQuantity":3700,"couponStartTime":1595001600,"couponEndTime":1595519999,"mallClientAble":true,"planType":4,"zsDuoId":8505769,"planTypeAll":4,"promotionRate":250,"mallRate":30,"optId":1,"collected":false,"salesTip":"7737","descTxt":"高","servTxt":"高","lgstTxt":"高","isSceneAuth":true,"inBigSale":[10044,10037,10000,10098,10078,10289,10143],"haohuoCouponList":null,"timingUnitVO":null,"brandCouponList":[],"isOnsale":true,"isExtraMissionGoods":false,"unifiedTag":{"tagDTOs":[{"tagSeries":1,"tagId":3,"text":"退货包运费","color":"#FF5706","url":null},{"tagSeries":1,"tagId":24,"text":"极速退款","color":"#FF5706","url":null}],"iconDTOs":[]},"matchType":0},{"mallId":250959593,"mallName":"风格搭配","mallLogo":null,"qrCodeImageUrl":null,"merchantType":1,"hasCltCpn":false,"goodsId":140883902764,"goodsName":"夏季薄款短袖男韩版潮流反光蝴蝶印花半袖寸衫五分袖衬衫外套","goodsDesc":"夏季短袖男韩版潮流休闲宽松反光个性半袖衬","goodsImageUrl":"https://t00img.yangkeduo.com/goods/images/2020-06-19/9cf6351172fac8bbd6b0635fed93c476.jpeg","goodsThumbnailUrl":"https://t00img.yangkeduo.com/goods/images/2020-06-19/9cf6351172fac8bbd6b0635fed93c476.jpeg","minGroupPrice":31990,"categoryId":11841,"categoryName":"男装","goodsType":1,"hasPddCoupon":null,"hasCoupon":true,"couponMinOrderAmount":18000,"couponDiscount":18000,"couponTotalQuantity":5000,"couponRemainQuantity":190,"couponStartTime":1594742400,"couponEndTime":1595433599,"mallClientAble":true,"planType":4,"zsDuoId":1016291,"planTypeAll":4,"promotionRate":510,"mallRate":50,"optId":11841,"collected":false,"salesTip":"194","descTxt":"高","servTxt":"高","lgstTxt":"高","isSceneAuth":false,"inBigSale":[10098,10078],"haohuoCouponList":null,"timingUnitVO":null,"brandCouponList":[],"isOnsale":true,"isExtraMissionGoods":false,"unifiedTag":{"tagDTOs":[{"tagSeries":1,"tagId":3,"text":"退货包运费","color":"#FF5706","url":null},{"tagSeries":1,"tagId":24,"text":"极速退款","color":"#FF5706","url":null}],"iconDTOs":[]},"matchType":0},{"mallId":850381294,"mallName":"Safepure家居生活官方旗舰店","mallLogo":null,"qrCodeImageUrl":null,"merchantType":3,"hasCltCpn":false,"goodsId":150068547702,"goodsName":"【送洗手液】正品香皂特香洗澡洗脸皂芦荟洗手家用洁面皂肥皂批发","goodsDesc":"【送洗手液】正品香皂特香洗澡洗脸皂芦荟洗手家用洁面皂肥皂批发","goodsImageUrl":"https://t00img.yangkeduo.com/goods/images/2020-07-09/a4dd035f35f26c6d2831c6ee644aa401.jpeg","goodsThumbnailUrl":"https://t00img.yangkeduo.com/goods/images/2020-07-09/a4dd035f35f26c6d2831c6ee644aa401.jpeg","minGroupPrice":8900,"categoryId":10110,"categoryName":"洗护","goodsType":1,"hasPddCoupon":null,"hasCoupon":true,"couponMinOrderAmount":4000,"couponDiscount":4000,"couponTotalQuantity":10000,"couponRemainQuantity":5600,"couponStartTime":1595001600,"couponEndTime":1595260799,"mallClientAble":true,"planType":4,"zsDuoId":9316815,"planTypeAll":4,"promotionRate":200,"mallRate":10,"optId":10110,"collected":false,"salesTip":"1813","descTxt":"高","servTxt":"高","lgstTxt":"高","isSceneAuth":true,"inBigSale":[10098,10078],"haohuoCouponList":null,"timingUnitVO":null,"brandCouponList":[],"isOnsale":true,"isExtraMissionGoods":false,"unifiedTag":{"tagDTOs":[{"tagSeries":1,"tagId":3,"text":"退货包运费","color":"#FF5706","url":null}],"iconDTOs":[]},"matchType":0},{"mallId":600610834,"mallName":"杨小姐杂货铺子","mallLogo":null,"qrCodeImageUrl":null,"merchantType":1,"hasCltCpn":false,"goodsId":128567732935,"goodsName":"米果糙米卷夹心能量棒零食批发休闲零食非油炸台湾米卷好吃的零食","goodsDesc":"米果糙米卷夹心能量棒零食批发休闲零食非油炸台湾米卷好吃的零食","goodsImageUrl":"https://t00img.yangkeduo.com/goods/images/2020-07-04/821c10d7d9b4b3fe4a13b7019b4be3f3.jpeg","goodsThumbnailUrl":"https://t00img.yangkeduo.com/goods/images/2020-07-04/821c10d7d9b4b3fe4a13b7019b4be3f3.jpeg","minGroupPrice":5890,"categoryId":1,"categoryName":"食品","goodsType":1,"hasPddCoupon":null,"hasCoupon":true,"couponMinOrderAmount":3000,"couponDiscount":3000,"couponTotalQuantity":10000,"couponRemainQuantity":7000,"couponStartTime":1595088000,"couponEndTime":1595433599,"mallClientAble":true,"planType":4,"zsDuoId":10630603,"planTypeAll":4,"promotionRate":210,"mallRate":10,"optId":1,"collected":false,"salesTip":"6514","descTxt":"高","servTxt":"高","lgstTxt":"高","isSceneAuth":true,"inBigSale":[10044,10037,10289,10078,10142,10098,10097],"haohuoCouponList":null,"timingUnitVO":null,"brandCouponList":[],"isOnsale":true,"isExtraMissionGoods":false,"unifiedTag":{"tagDTOs":[{"tagSeries":1,"tagId":24,"text":"极速退款","color":"#FF5706","url":null}],"iconDTOs":[]},"matchType":0},{"mallId":533667318,"mallName":"新美农水果生鲜店","mallLogo":null,"qrCodeImageUrl":null,"merchantType":6,"hasCltCpn":false,"goodsId":145683169470,"goodsName":"大荔冬枣脆甜多汁当季水果新鲜1/3/5斤鲜枣果园整箱批发非红枣","goodsDesc":"大荔冬枣脆甜多汁当季水果新鲜1/3/5斤鲜枣果园整箱批发非红枣","goodsImageUrl":"https://t00img.yangkeduo.com/goods/images/2020-07-14/fb30fc6744aa86fe1053758c82e89f3a.jpeg","goodsThumbnailUrl":"https://t00img.yangkeduo.com/goods/images/2020-07-14/fb30fc6744aa86fe1053758c82e89f3a.jpeg","minGroupPrice":11900,"categoryId":10696,"categoryName":"海淘","goodsType":1,"hasPddCoupon":null,"hasCoupon":true,"couponMinOrderAmount":4000,"couponDiscount":4000,"couponTotalQuantity":1000,"couponRemainQuantity":900,"couponStartTime":1595174400,"couponEndTime":1595606399,"mallClientAble":true,"planType":4,"zsDuoId":8614049,"planTypeAll":4,"promotionRate":210,"mallRate":50,"optId":10696,"collected":false,"salesTip":"687","descTxt":"高","servTxt":"高","lgstTxt":"高","isSceneAuth":false,"inBigSale":[10078,10037,10098],"haohuoCouponList":null,"timingUnitVO":null,"brandCouponList":[],"isOnsale":true,"isExtraMissionGoods":false,"unifiedTag":{"tagDTOs":[{"tagSeries":1,"tagId":9,"text":"坏果包赔","color":"#FF5706","url":null},{"tagSeries":1,"tagId":24,"text":"极速退款","color":"#FF5706","url":null}],"iconDTOs":[]},"matchType":0},{"mallId":537494211,"mallName":"三联生活家居馆","mallLogo":null,"qrCodeImageUrl":null,"merchantType":6,"hasCltCpn":false,"goodsId":133358314927,"goodsName":"蓝泡泡洁厕灵厕所除臭洁厕宝马桶清洁剂厕所家庭卫生间清香除异味","goodsDesc":"蓝泡泡洁厕灵厕所除臭洁厕宝马桶清洁剂厕所家庭卫生间清香除异味","goodsImageUrl":"https://t00img.yangkeduo.com/goods/images/2020-06-23/3a9c34bba7e6ed3228a19798bbbd06d0.jpeg","goodsThumbnailUrl":"https://t00img.yangkeduo.com/goods/images/2020-06-23/3a9c34bba7e6ed3228a19798bbbd06d0.jpeg","minGroupPrice":4070,"categoryId":10110,"categoryName":"洗护","goodsType":1,"hasPddCoupon":null,"hasCoupon":true,"couponMinOrderAmount":2000,"couponDiscount":2000,"couponTotalQuantity":4000,"couponRemainQuantity":2500,"couponStartTime":1595088000,"couponEndTime":1596211199,"mallClientAble":true,"planType":4,"zsDuoId":1887340,"planTypeAll":5,"promotionRate":250,"mallRate":10,"optId":10110,"collected":false,"salesTip":"1.7万","descTxt":"高","servTxt":"高","lgstTxt":"高","isSceneAuth":true,"inBigSale":[10294,10097,10044,10096,10277,10298,10140,10311,10138,10142,10098,10289,10127,10037,10000,10078],"haohuoCouponList":null,"timingUnitVO":null,"brandCouponList":[],"isOnsale":true,"isExtraMissionGoods":false,"unifiedTag":{"tagDTOs":[{"tagSeries":1,"tagId":3,"text":"退货包运费","color":"#FF5706","url":null},{"tagSeries":1,"tagId":24,"text":"极速退款","color":"#FF5706","url":null}],"iconDTOs":[{"tagSeries":2,"tagId":20013,"text":null,"color":"","url":"https://commimg.pddpic.com/oms_img_ng/2020-07-06/b763cbc5-a35d-4102-a57c-eaaba441c7b8.png"}]},"matchType":0},{"mallId":633045998,"mallName":"晋源图书专营店","mallLogo":null,"qrCodeImageUrl":null,"merchantType":5,"hasCltCpn":false,"goodsId":109551534886,"goodsName":"小学试卷二年级上册语文数学试卷人教版同步训练三年级一四五六年","goodsDesc":"小学试卷二年级上册语文数学试卷人教版同步训练三年级一四五六年","goodsImageUrl":"https://t00img.yangkeduo.com/goods/images/2020-07-03/262bebef62500e44904aee82deb668b3.jpeg","goodsThumbnailUrl":"https://t00img.yangkeduo.com/goods/images/2020-07-03/262bebef62500e44904aee82deb668b3.jpeg","minGroupPrice":2940,"categoryId":21888,"categoryName":"图书","goodsType":1,"hasPddCoupon":null,"hasCoupon":true,"couponMinOrderAmount":1000,"couponDiscount":1000,"couponTotalQuantity":10000,"couponRemainQuantity":8000,"couponStartTime":1595088000,"couponEndTime":1595519999,"mallClientAble":true,"planType":4,"zsDuoId":10686946,"planTypeAll":5,"promotionRate":280,"mallRate":30,"optId":21888,"collected":false,"salesTip":"1.3万","descTxt":"高","servTxt":"高","lgstTxt":"高","isSceneAuth":false,"inBigSale":[31,10064,10037,24,10000,10078,10289,10097,21,10044,10098],"haohuoCouponList":null,"timingUnitVO":null,"brandCouponList":[],"isOnsale":true,"isExtraMissionGoods":false,"unifiedTag":{"tagDTOs":[{"tagSeries":1,"tagId":3,"text":"退货包运费","color":"#FF5706","url":null},{"tagSeries":1,"tagId":24,"text":"极速退款","color":"#FF5706","url":null}],"iconDTOs":[]},"matchType":0},{"mallId":883225,"mallName":"优诺家纺","mallLogo":null,"qrCodeImageUrl":null,"merchantType":1,"hasCltCpn":false,"goodsId":115779828539,"goodsName":"毛巾残次品按斤卖特价批发家用清洁抹布吸水瑕疵成人方巾吸水巾","goodsDesc":"毛巾残次品按斤卖特价批发家用清洁抹布吸水瑕疵成人方巾吸水巾","goodsImageUrl":"https://t00img.yangkeduo.com/goods/images/2020-07-13/432d6756fe26872015db97568ddddfa4.jpeg","goodsThumbnailUrl":"https://t00img.yangkeduo.com/goods/images/2020-07-13/432d6756fe26872015db97568ddddfa4.jpeg","minGroupPrice":12210,"categoryId":9831,"categoryName":"百货","goodsType":1,"hasPddCoupon":null,"hasCoupon":true,"couponMinOrderAmount":6000,"couponDiscount":6000,"couponTotalQuantity":10000,"couponRemainQuantity":2900,"couponStartTime":1594915200,"couponEndTime":1595606399,"mallClientAble":true,"planType":4,"zsDuoId":9539749,"planTypeAll":4,"promotionRate":520,"mallRate":10,"optId":9831,"collected":false,"salesTip":"3865","descTxt":"高","servTxt":"高","lgstTxt":"高","isSceneAuth":true,"inBigSale":[10097,10289,10098,10078,10044,10037],"haohuoCouponList":null,"timingUnitVO":null,"brandCouponList":[],"isOnsale":true,"isExtraMissionGoods":false,"unifiedTag":{"tagDTOs":[{"tagSeries":1,"tagId":3,"text":"退货包运费","color":"#FF5706","url":null}],"iconDTOs":[]},"matchType":0},{"mallId":533639715,"mallName":"植泊萃护肤旗舰店","mallLogo":null,"qrCodeImageUrl":null,"merchantType":3,"hasCltCpn":false,"goodsId":54863250938,"goodsName":"天然手工皂精油皂香皂除螨皂补水沐浴去黑控油洗脸皂美白祛痘肥皂","goodsDesc":"纯手工皂每块100克左右。本店所有产品均系正规厂家出品,保证质量,请亲放心购买!坚持使用可以淡化黑色素、除螨虫、去黑头、紧致毛孔、去除痘痘、去痘印、清理粉刺等。改善皮肤粗糙、干燥脱皮,毛孔粗大、油光泛滥、瘙痒暗沉、黑头色斑等皮肤问题!!手工皂洗脸.洗手.洗澡男女老少婴幼儿都可使用!使用方法:湿润肌肤后,使用起泡网或者用手加水揉出细腻丰富的泡沫涂抹至所需清洁处,按摩片刻用清水洗净即可哦! 温馨提示,【三块香型自由组合不联系客服备注的 仓库选择3块皂随机发 五块香型自由组合。不联系客服备注的 仓库选择5块皂随机发。十块香型自由组合不联系客服备注的,仓库选择随机发货哦。 介意者慎拍此选项 】","goodsImageUrl":"https://t00img.yangkeduo.com/goods/images/2019-10-25/e77955915138e25e02dae36b3c2fc3a1.jpeg","goodsThumbnailUrl":"https://t00img.yangkeduo.com/goods/images/2019-10-25/e77955915138e25e02dae36b3c2fc3a1.jpeg","minGroupPrice":14900,"categoryId":16,"categoryName":"美妆","goodsType":1,"hasPddCoupon":null,"hasCoupon":true,"couponMinOrderAmount":10000,"couponDiscount":10000,"couponTotalQuantity":5000,"couponRemainQuantity":2500,"couponStartTime":1595001600,"couponEndTime":1595433599,"mallClientAble":true,"planType":4,"zsDuoId":8638825,"planTypeAll":4,"promotionRate":200,"mallRate":10,"optId":16,"collected":false,"salesTip":"1.2万","descTxt":"高","servTxt":"高","lgstTxt":"高","isSceneAuth":true,"inBigSale":[10127,10064,10142,10078,10138,10296,10097,10294,10140,10098,10037,10289,10290,10096,10281,10000,10311,10101,10309,10044,10277],"haohuoCouponList":null,"timingUnitVO":null,"brandCouponList":[],"isOnsale":true,"isExtraMissionGoods":false,"unifiedTag":{"tagDTOs":[{"tagSeries":1,"tagId":3,"text":"退货包运费","color":"#FF5706","url":null},{"tagSeries":1,"tagId":24,"text":"极速退款","color":"#FF5706","url":null}],"iconDTOs":[{"tagSeries":2,"tagId":20013,"text":null,"color":"","url":"https://commimg.pddpic.com/oms_img_ng/2020-07-06/b763cbc5-a35d-4102-a57c-eaaba441c7b8.png"}]},"matchType":0},{"mallId":427769514,"mallName":"螺飘飘旗舰店","mallLogo":null,"qrCodeImageUrl":null,"merchantType":3,"hasCltCpn":false,"goodsId":129817993580,"goodsName":"【领券立减10】黑麦面包全麦面包早餐手撕吐司片代餐食品休闲零食","goodsDesc":"【领券立减10】黑麦面包全麦面包早餐手撕吐司片代餐食品休闲零食","goodsImageUrl":"https://t00img.yangkeduo.com/goods/images/2020-05-30/ddef9a3c90d2274a7d3ec2951cd6d534.jpeg","goodsThumbnailUrl":"https://t00img.yangkeduo.com/goods/images/2020-05-30/ddef9a3c90d2274a7d3ec2951cd6d534.jpeg","minGroupPrice":15800,"categoryId":11876,"categoryName":"零食/坚果/特产","goodsType":1,"hasPddCoupon":null,"hasCoupon":true,"couponMinOrderAmount":11000,"couponDiscount":11000,"couponTotalQuantity":10000,"couponRemainQuantity":8000,"couponStartTime":1595001600,"couponEndTime":1595433599,"mallClientAble":true,"planType":2,"zsDuoId":0,"planTypeAll":0,"promotionRate":400,"mallRate":10,"optId":11876,"collected":false,"salesTip":"1503","descTxt":"高","servTxt":"高","lgstTxt":"高","isSceneAuth":true,"inBigSale":[10138,10304,10311,21,10296,10142,10306,10140,10096,10286,10294,10078,10127,10277,10064,10098,10044],"haohuoCouponList":null,"timingUnitVO":null,"brandCouponList":[],"isOnsale":true,"isExtraMissionGoods":false,"unifiedTag":{"tagDTOs":[{"tagSeries":1,"tagId":3,"text":"退货包运费","color":"#FF5706","url":null},{"tagSeries":1,"tagId":24,"text":"极速退款","color":"#FF5706","url":null}],"iconDTOs":[{"tagSeries":2,"tagId":20013,"text":null,"color":"","url":"https://commimg.pddpic.com/oms_img_ng/2020-07-06/b763cbc5-a35d-4102-a57c-eaaba441c7b8.png"}]},"matchType":0},{"mallId":616722688,"mallName":"恒农食品专营店","mallLogo":null,"qrCodeImageUrl":null,"merchantType":5,"hasCltCpn":false,"goodsId":146686635554,"goodsName":"萌趣小麻花零食独立包装黑糖海苔椒盐芝麻香葱散装办公室休闲食品","goodsDesc":"萌趣小麻花零食独立包装黑糖海苔椒盐芝麻香葱散装办公室休闲食品","goodsImageUrl":"https://t00img.yangkeduo.com/goods/images/2020-07-02/fef8fde61c2062a326efdfecbbcd6036.jpeg","goodsThumbnailUrl":"https://t00img.yangkeduo.com/goods/images/2020-07-02/fef8fde61c2062a326efdfecbbcd6036.jpeg","minGroupPrice":5600,"categoryId":1,"categoryName":"食品","goodsType":1,"hasPddCoupon":null,"hasCoupon":true,"couponMinOrderAmount":3000,"couponDiscount":3000,"couponTotalQuantity":2000,"couponRemainQuantity":1900,"couponStartTime":1595174400,"couponEndTime":1595347199,"mallClientAble":true,"planType":4,"zsDuoId":8495561,"planTypeAll":4,"promotionRate":200,"mallRate":10,"optId":1,"collected":false,"salesTip":"6901","descTxt":"高","servTxt":"高","lgstTxt":"高","isSceneAuth":true,"inBigSale":[10078,10289,10097,10098,10044],"haohuoCouponList":null,"timingUnitVO":null,"brandCouponList":[],"isOnsale":true,"isExtraMissionGoods":false,"unifiedTag":{"tagDTOs":[{"tagSeries":1,"tagId":3,"text":"退货包运费","color":"#FF5706","url":null}],"iconDTOs":[]},"matchType":0},{"mallId":476025395,"mallName":"韩奏旗舰店","mallLogo":null,"qrCodeImageUrl":null,"merchantType":3,"hasCltCpn":false,"goodsId":59848139217,"goodsName":"【2包装】洗脸巾抽取式一次性卸妆纯棉加厚洁面毛巾婴儿干湿两用","goodsDesc":"【2包装】洗脸巾抽取式一次性卸妆纯棉加厚洁面毛巾婴儿干湿两用","goodsImageUrl":"https://t00img.yangkeduo.com/goods/images/2020-07-19/2c2b2c532a1ad506ca613aa69a5e1b49.jpeg","goodsThumbnailUrl":"https://t00img.yangkeduo.com/goods/images/2020-07-19/2c2b2c532a1ad506ca613aa69a5e1b49.jpeg","minGroupPrice":4990,"categoryId":12,"categoryName":"海淘","goodsType":1,"hasPddCoupon":null,"hasCoupon":true,"couponMinOrderAmount":3000,"couponDiscount":3000,"couponTotalQuantity":10000,"couponRemainQuantity":5300,"couponStartTime":1595001600,"couponEndTime":1595433599,"mallClientAble":true,"planType":4,"zsDuoId":8192821,"planTypeAll":4,"promotionRate":200,"mallRate":10,"optId":12,"collected":false,"salesTip":"10万+","descTxt":"高","servTxt":"高","lgstTxt":"高","isSceneAuth":true,"inBigSale":[10311,10277,10290,21,10289,10098,10101,10140,10044,10096,10127,10296,10037,10000,10138,10078,10309],"haohuoCouponList":null,"timingUnitVO":null,"brandCouponList":[],"isOnsale":true,"isExtraMissionGoods":false,"unifiedTag":{"tagDTOs":[{"tagSeries":1,"tagId":24,"text":"极速退款","color":"#FF5706","url":null}],"iconDTOs":[{"tagSeries":2,"tagId":20013,"text":null,"color":"","url":"https://commimg.pddpic.com/oms_img_ng/2020-07-06/b763cbc5-a35d-4102-a57c-eaaba441c7b8.png"}]},"matchType":0},{"mallId":993291688,"mallName":"恒缘医疗器械专营店","mallLogo":null,"qrCodeImageUrl":null,"merchantType":5,"hasCltCpn":false,"goodsId":150466131054,"goodsName":"脚臭神器脚臭粉除脚臭脚汗脚痒鞋袜臭去脚臭克星臭脚粉泡脚足光粉","goodsDesc":"脚臭神器脚臭粉除脚臭脚汗脚痒鞋袜臭去脚臭克星臭脚粉泡脚足光粉","goodsImageUrl":"https://t00img.yangkeduo.com/goods/images/2020-07-19/c2ccf1e3490f8d150a0fb17ef354d1e0.jpeg","goodsThumbnailUrl":"https://t00img.yangkeduo.com/goods/images/2020-07-19/c2ccf1e3490f8d150a0fb17ef354d1e0.jpeg","minGroupPrice":8900,"categoryId":10223,"categoryName":"健康","goodsType":1,"hasPddCoupon":null,"hasCoupon":true,"couponMinOrderAmount":7000,"couponDiscount":7000,"couponTotalQuantity":10000,"couponRemainQuantity":8000,"couponStartTime":1595088000,"couponEndTime":1595519999,"mallClientAble":true,"planType":4,"zsDuoId":8355904,"planTypeAll":4,"promotionRate":500,"mallRate":10,"optId":10223,"collected":false,"salesTip":"2607","descTxt":"高","servTxt":"高","lgstTxt":"高","isSceneAuth":true,"inBigSale":[10044,10078,10098],"haohuoCouponList":null,"timingUnitVO":null,"brandCouponList":[],"isOnsale":true,"isExtraMissionGoods":false,"unifiedTag":null,"matchType":0},{"mallId":241794866,"mallName":"捷安娜家居生活旗舰店","mallLogo":null,"qrCodeImageUrl":null,"merchantType":3,"hasCltCpn":false,"goodsId":150589793027,"goodsName":"一次性手套食品级薄膜加厚餐饮小吃美发儿童家用防油防水手套批发","goodsDesc":"一次性手套食品级薄膜加厚餐饮小吃美发儿童家用防油防水手套批发","goodsImageUrl":"https://t00img.yangkeduo.com/goods/images/2020-07-10/965e4d9a6b3e0d7ef278cbffedab816b.jpeg","goodsThumbnailUrl":"https://t00img.yangkeduo.com/goods/images/2020-07-10/965e4d9a6b3e0d7ef278cbffedab816b.jpeg","minGroupPrice":6690,"categoryId":20527,"categoryName":"百货","goodsType":1,"hasPddCoupon":null,"hasCoupon":true,"couponMinOrderAmount":5000,"couponDiscount":5000,"couponTotalQuantity":2000,"couponRemainQuantity":1100,"couponStartTime":1595174400,"couponEndTime":1595606399,"mallClientAble":true,"planType":4,"zsDuoId":10522123,"planTypeAll":4,"promotionRate":200,"mallRate":1,"optId":20527,"collected":false,"salesTip":"1497","descTxt":"高","servTxt":"高","lgstTxt":"高","isSceneAuth":true,"inBigSale":[10044,10078,10098,21,10037],"haohuoCouponList":null,"timingUnitVO":null,"brandCouponList":[],"isOnsale":true,"isExtraMissionGoods":false,"unifiedTag":{"tagDTOs":[{"tagSeries":1,"tagId":3,"text":"退货包运费","color":"#FF5706","url":null},{"tagSeries":1,"tagId":24,"text":"极速退款","color":"#FF5706","url":null}],"iconDTOs":[]},"matchType":0},{"mallId":935329097,"mallName":"禾硕香优选","mallLogo":null,"qrCodeImageUrl":null,"merchantType":6,"hasCltCpn":false,"goodsId":152350522780,"goodsName":"百家鲜金标耗油家用炒菜调味品提味增鲜烧烤蘸料火锅调料破损包赔","goodsDesc":"百家鲜金标耗油家用炒菜调味品提味增鲜烧烤蘸料火锅调料破损包赔","goodsImageUrl":"https://t00img.yangkeduo.com/goods/images/2020-07-14/f561cd472bdfa7eb2399de2015abdd16.jpeg","goodsThumbnailUrl":"https://t00img.yangkeduo.com/goods/images/2020-07-14/f561cd472bdfa7eb2399de2015abdd16.jpeg","minGroupPrice":7000,"categoryId":1,"categoryName":"食品","goodsType":1,"hasPddCoupon":null,"hasCoupon":true,"couponMinOrderAmount":2000,"couponDiscount":2000,"couponTotalQuantity":1000,"couponRemainQuantity":600,"couponStartTime":1595174400,"couponEndTime":1595347199,"mallClientAble":true,"planType":4,"zsDuoId":9294756,"planTypeAll":4,"promotionRate":200,"mallRate":10,"optId":1,"collected":false,"salesTip":"2687","descTxt":"高","servTxt":"高","lgstTxt":"高","isSceneAuth":true,"inBigSale":[10098,10078,10097,10289,10044],"haohuoCouponList":null,"timingUnitVO":null,"brandCouponList":[],"isOnsale":true,"isExtraMissionGoods":false,"unifiedTag":null,"matchType":0},{"mallId":141504728,"mallName":"等味来食品旗舰店","mallLogo":null,"qrCodeImageUrl":null,"merchantType":3,"hasCltCpn":false,"goodsId":58916527682,"goodsName":"锅主老火锅底料重庆火锅底料50g/500g牛油火锅底料麻辣麻辣烫底料【7月24日发完】","goodsDesc":"锅主老火锅底料重庆火锅底料50g/500g牛油火锅底料麻辣麻辣烫底料","goodsImageUrl":"https://t00img.yangkeduo.com/goods/images/2020-07-16/5dc4f1ae602030bcd6877e1c738ee916.jpeg","goodsThumbnailUrl":"https://t00img.yangkeduo.com/goods/images/2020-07-16/5dc4f1ae602030bcd6877e1c738ee916.jpeg","minGroupPrice":2900,"categoryId":1,"categoryName":"食品","goodsType":1,"hasPddCoupon":null,"hasCoupon":true,"couponMinOrderAmount":1000,"couponDiscount":1000,"couponTotalQuantity":10000,"couponRemainQuantity":9000,"couponStartTime":1595174400,"couponEndTime":1595519999,"mallClientAble":false,"planType":4,"zsDuoId":8877763,"planTypeAll":4,"promotionRate":200,"mallRate":10,"optId":1,"collected":false,"salesTip":"7156","descTxt":"高","servTxt":"高","lgstTxt":"高","isSceneAuth":true,"inBigSale":[10098,10078],"haohuoCouponList":null,"timingUnitVO":null,"brandCouponList":[],"isOnsale":true,"isExtraMissionGoods":false,"unifiedTag":{"tagDTOs":[{"tagSeries":1,"tagId":24,"text":"极速退款","color":"#FF5706","url":null}],"iconDTOs":[]},"matchType":0},{"mallId":665032493,"mallName":"正张官方旗舰店","mallLogo":null,"qrCodeImageUrl":null,"merchantType":3,"hasCltCpn":false,"goodsId":6329218312,"goodsName":"正品电热蚊香液驱蚊液无味婴儿孕妇电蚊香器防蚊卧室家用插电式","goodsDesc":"【拒绝偷工减料,超大瓶】【液无小包装请慎拍,但是不影响质量】【有安全合格证质检报告 用的放心】电热蚊香液,是采用纯自然植物成分,自然除虫菊素为原料配置而成的一种驱蚊液体,该液体通过芯棒的连接在电子恒温加热器的均匀作用下进行有效发挥发到使用空间,从而达到灭蚊的效果,有点1 使用方便,无需天天换药。一瓶45ml药业可有效使用45天,只需要简单的开启或关闭开关即可。2药液可以全部无浪费用完,对环境无污染,3电源接通后有知识灯,便于提醒,即使在黑暗中使用也不会踢到,打翻,4使用安全,正常情况下人的肢体是触摸不到发热器件及药液的。5使用过程中,不会产生烟和气味。对使用空间 不会造成不适感。6纯自然杀虫制品,具备无残留,无污染,安全卫生等特点,属于卢瑟环保产品,该产品由于以上众多有点,已经慢慢在替代传统蚊香而渐渐成为新式家用卫生驱蚊用品","goodsImageUrl":"https://t00img.yangkeduo.com/goods/images/2019-04-11/3fed74e4293e14a87ac5466b39cff820.jpeg","goodsThumbnailUrl":"https://t00img.yangkeduo.com/goods/images/2019-04-11/3fed74e4293e14a87ac5466b39cff820.jpeg","minGroupPrice":3400,"categoryId":10110,"categoryName":"洗护","goodsType":1,"hasPddCoupon":null,"hasCoupon":true,"couponMinOrderAmount":1000,"couponDiscount":1000,"couponTotalQuantity":10000,"couponRemainQuantity":4400,"couponStartTime":1595001600,"couponEndTime":1595519999,"mallClientAble":true,"planType":4,"zsDuoId":8988332,"planTypeAll":4,"promotionRate":710,"mallRate":10,"optId":10110,"collected":false,"salesTip":"6.2万","descTxt":"高","servTxt":"高","lgstTxt":"高","isSceneAuth":true,"inBigSale":[10097,10078,10044,10098,10037,10289],"haohuoCouponList":null,"timingUnitVO":null,"brandCouponList":[],"isOnsale":true,"isExtraMissionGoods":false,"unifiedTag":{"tagDTOs":[{"tagSeries":1,"tagId":3,"text":"退货包运费","color":"#FF5706","url":null},{"tagSeries":1,"tagId":24,"text":"极速退款","color":"#FF5706","url":null}],"iconDTOs":[]},"matchType":0},{"mallId":861646796,"mallName":"宜婴恒乐专卖店","mallLogo":null,"qrCodeImageUrl":null,"merchantType":4,"hasCltCpn":false,"goodsId":142828107061,"goodsName":"宜婴宝宝成长裤空调纸尿裤试用装 超薄拉拉裤尿不湿透气亲肤6片装","goodsDesc":"宜婴宝宝成长裤空调纸尿裤试用装 超薄拉拉裤尿不湿透气亲肤6片装","goodsImageUrl":"https://t00img.yangkeduo.com/goods/images/2020-06-24/28a92d3602f9c7235098bdf58dc72381.jpeg","goodsThumbnailUrl":"https://t00img.yangkeduo.com/goods/images/2020-06-24/28a92d3602f9c7235098bdf58dc72381.jpeg","minGroupPrice":9900,"categoryId":23010,"categoryName":"母婴","goodsType":1,"hasPddCoupon":null,"hasCoupon":true,"couponMinOrderAmount":4000,"couponDiscount":4000,"couponTotalQuantity":3000,"couponRemainQuantity":1700,"couponStartTime":1595001600,"couponEndTime":1595433599,"mallClientAble":true,"planType":4,"zsDuoId":8550520,"planTypeAll":4,"promotionRate":500,"mallRate":100,"optId":23010,"collected":false,"salesTip":"1万","descTxt":"高","servTxt":"高","lgstTxt":"高","isSceneAuth":false,"inBigSale":[10078,10098,10037,10000,31,10044,10289,24,21,10097],"haohuoCouponList":null,"timingUnitVO":null,"brandCouponList":[],"isOnsale":true,"isExtraMissionGoods":false,"unifiedTag":{"tagDTOs":[{"tagSeries":1,"tagId":3,"text":"退货包运费","color":"#FF5706","url":null},{"tagSeries":1,"tagId":24,"text":"极速退款","color":"#FF5706","url":null}],"iconDTOs":[]},"matchType":0},{"mallId":1930422,"mallName":"贝童乐玩具","mallLogo":null,"qrCodeImageUrl":null,"merchantType":1,"hasCltCpn":false,"goodsId":153893661732,"goodsName":"儿童益智脑力开发玩具汉堡魔方手指陀螺小魔豆 抖音成人减压神器","goodsDesc":"儿童益智脑力开发玩具汉堡魔方手指陀螺小魔豆 抖音成人减压神器","goodsImageUrl":"https://t00img.yangkeduo.com/goods/images/2020-07-17/d7640e69b06dd390f9e97f7fe0829640.jpeg","goodsThumbnailUrl":"https://t00img.yangkeduo.com/goods/images/2020-07-17/d7640e69b06dd390f9e97f7fe0829640.jpeg","minGroupPrice":8900,"categoryId":10696,"categoryName":"海淘","goodsType":1,"hasPddCoupon":null,"hasCoupon":true,"couponMinOrderAmount":5000,"couponDiscount":5000,"couponTotalQuantity":10000,"couponRemainQuantity":4000,"couponStartTime":1595001600,"couponEndTime":1595347199,"mallClientAble":false,"planType":4,"zsDuoId":9199188,"planTypeAll":4,"promotionRate":200,"mallRate":10,"optId":10696,"collected":false,"salesTip":"3503","descTxt":"高","servTxt":"高","lgstTxt":"高","isSceneAuth":true,"inBigSale":[10037,10078,10098],"haohuoCouponList":null,"timingUnitVO":null,"brandCouponList":[],"isOnsale":true,"isExtraMissionGoods":false,"unifiedTag":null,"matchType":0},{"mallId":693777,"mallName":"创宁食品专营店","mallLogo":null,"qrCodeImageUrl":null,"merchantType":5,"hasCltCpn":false,"goodsId":128248415351,"goodsName":"丰阳谷米ni酥小米花生酥黑米酥米花酥330g休闲零食大礼包零食小吃","goodsDesc":"丰阳谷米ni酥小米花生酥黑米酥米花酥330g休闲零食大礼包零食小吃","goodsImageUrl":"https://t00img.yangkeduo.com/goods/images/2020-06-01/ca9f335d088f52db8512948ec97ad748.jpeg","goodsThumbnailUrl":"https://t00img.yangkeduo.com/goods/images/2020-06-01/ca9f335d088f52db8512948ec97ad748.jpeg","minGroupPrice":10770,"categoryId":1,"categoryName":"食品","goodsType":1,"hasPddCoupon":null,"hasCoupon":true,"couponMinOrderAmount":7000,"couponDiscount":7000,"couponTotalQuantity":3000,"couponRemainQuantity":1300,"couponStartTime":1595088000,"couponEndTime":1595260799,"mallClientAble":true,"planType":4,"zsDuoId":8559921,"planTypeAll":4,"promotionRate":200,"mallRate":100,"optId":1,"collected":false,"salesTip":"2438","descTxt":"高","servTxt":"高","lgstTxt":"高","isSceneAuth":true,"inBigSale":[10037,10098,10078,10289,10000,10064,10044],"haohuoCouponList":null,"timingUnitVO":null,"brandCouponList":[],"isOnsale":true,"isExtraMissionGoods":false,"unifiedTag":{"tagDTOs":[{"tagSeries":1,"tagId":3,"text":"退货包运费","color":"#FF5706","url":null},{"tagSeries":1,"tagId":24,"text":"极速退款","color":"#FF5706","url":null}],"iconDTOs":[]},"matchType":0},{"mallId":223927,"mallName":"索韩美妆个护专营店","mallLogo":null,"qrCodeImageUrl":null,"merchantType":5,"hasCltCpn":false,"goodsId":85835727014,"goodsName":"【一支涂三色】三色口红抖音同款不沾杯不掉色孕妇唇膏滋润学生女","goodsDesc":"【一支涂三色】三色口红抖音同款不沾杯不掉色孕妇唇膏滋润学生女","goodsImageUrl":"https://t00img.yangkeduo.com/goods/images/2020-07-03/c4a2a7c701dfa9c19b4d0e0f25f321f1.jpeg","goodsThumbnailUrl":"https://t00img.yangkeduo.com/goods/images/2020-07-03/c4a2a7c701dfa9c19b4d0e0f25f321f1.jpeg","minGroupPrice":11800,"categoryId":12,"categoryName":"海淘","goodsType":1,"hasPddCoupon":null,"hasCoupon":true,"couponMinOrderAmount":3000,"couponDiscount":3000,"couponTotalQuantity":6000,"couponRemainQuantity":5300,"couponStartTime":1595174400,"couponEndTime":1595606399,"mallClientAble":true,"planType":4,"zsDuoId":9345379,"planTypeAll":4,"promotionRate":610,"mallRate":10,"optId":12,"collected":false,"salesTip":"1.7万","descTxt":"高","servTxt":"高","lgstTxt":"高","isSceneAuth":true,"inBigSale":[10078,10064,10098,10044,10097,10037,21,10289],"haohuoCouponList":null,"timingUnitVO":null,"brandCouponList":[],"isOnsale":true,"isExtraMissionGoods":false,"unifiedTag":{"tagDTOs":[{"tagSeries":1,"tagId":24,"text":"极速退款","color":"#FF5706","url":null}],"iconDTOs":[]},"matchType":0},{"mallId":661868138,"mallName":"三镇优尚办公用品专营店","mallLogo":null,"qrCodeImageUrl":null,"merchantType":5,"hasCltCpn":false,"goodsId":134072367487,"goodsName":"正品金豪钢笔正姿练字成人男女小学生专用书写替换墨囊三年级官方","goodsDesc":"正品金豪钢笔正姿练字成人男女小学生专用书写替换墨囊三年级官方","goodsImageUrl":"https://t00img.yangkeduo.com/goods/images/2020-06-18/29ebc8877c168802d32384006ef03337.jpeg","goodsThumbnailUrl":"https://t00img.yangkeduo.com/goods/images/2020-06-18/29ebc8877c168802d32384006ef03337.jpeg","minGroupPrice":10900,"categoryId":11392,"categoryName":"文化用品","goodsType":1,"hasPddCoupon":null,"hasCoupon":true,"couponMinOrderAmount":8000,"couponDiscount":8000,"couponTotalQuantity":10000,"couponRemainQuantity":9000,"couponStartTime":1595174400,"couponEndTime":1595347199,"mallClientAble":true,"planType":4,"zsDuoId":1754446,"planTypeAll":4,"promotionRate":200,"mallRate":50,"optId":11392,"collected":false,"salesTip":"6088","descTxt":"高","servTxt":"高","lgstTxt":"高","isSceneAuth":true,"inBigSale":[10037,10097,10289,10044,10098,10078],"haohuoCouponList":null,"timingUnitVO":null,"brandCouponList":[],"isOnsale":true,"isExtraMissionGoods":false,"unifiedTag":{"tagDTOs":[{"tagSeries":1,"tagId":24,"text":"极速退款","color":"#FF5706","url":null}],"iconDTOs":[]},"matchType":0},{"mallId":77383,"mallName":"潮流来袭","mallLogo":null,"qrCodeImageUrl":null,"merchantType":1,"hasCltCpn":false,"goodsId":103267564742,"goodsName":"超大饭菜罩子盖菜罩可折叠餐桌罩剩菜食物罩防尘罩家用遮菜盖伞","goodsDesc":"超大饭菜罩子盖菜罩可折叠餐桌罩剩菜食物罩防尘罩家用遮菜盖伞","goodsImageUrl":"https://t00img.yangkeduo.com/goods/images/2020-04-16/70527283f9892eb9d3a3669f0734a86f.jpeg","goodsThumbnailUrl":"https://t00img.yangkeduo.com/goods/images/2020-04-16/70527283f9892eb9d3a3669f0734a86f.jpeg","minGroupPrice":3890,"categoryId":11463,"categoryName":"收纳整理","goodsType":1,"hasPddCoupon":null,"hasCoupon":true,"couponMinOrderAmount":1000,"couponDiscount":1000,"couponTotalQuantity":5000,"couponRemainQuantity":1100,"couponStartTime":1595001600,"couponEndTime":1595433599,"mallClientAble":true,"planType":4,"zsDuoId":9205343,"planTypeAll":4,"promotionRate":200,"mallRate":10,"optId":11463,"collected":false,"salesTip":"3万","descTxt":"高","servTxt":"高","lgstTxt":"高","isSceneAuth":true,"inBigSale":[10097,10311,21,10000,10044,10098,10064,10127,10140,10277,10078,10138,10298,10096,10294],"haohuoCouponList":null,"timingUnitVO":null,"brandCouponList":[],"isOnsale":true,"isExtraMissionGoods":false,"unifiedTag":{"tagDTOs":[{"tagSeries":1,"tagId":3,"text":"退货包运费","color":"#FF5706","url":null}],"iconDTOs":[{"tagSeries":2,"tagId":20013,"text":null,"color":"","url":"https://commimg.pddpic.com/oms_img_ng/2020-07-06/b763cbc5-a35d-4102-a57c-eaaba441c7b8.png"}]},"matchType":0},{"mallId":250672206,"mallName":"森林木居家生活馆","mallLogo":null,"qrCodeImageUrl":null,"merchantType":6,"hasCltCpn":true,"goodsId":144269466410,"goodsName":"脚气偏方脚气膏治脚气止痒水泡脚臭脱皮烂脚丫香港脚真菌男女通用","goodsDesc":"脚气偏方脚气膏治脚气止痒水泡脚臭脱皮烂脚丫香港脚真菌男女通用","goodsImageUrl":"https://t00img.yangkeduo.com/goods/images/2020-06-27/a9979a67d23b0826e86dbcf76fed07c1.jpeg","goodsThumbnailUrl":"https://t00img.yangkeduo.com/goods/images/2020-06-27/a9979a67d23b0826e86dbcf76fed07c1.jpeg","minGroupPrice":18980,"categoryId":10110,"categoryName":"洗护","goodsType":1,"hasPddCoupon":null,"hasCoupon":true,"couponMinOrderAmount":15000,"couponDiscount":15000,"couponTotalQuantity":5000,"couponRemainQuantity":4200,"couponStartTime":1595088000,"couponEndTime":1595347199,"mallClientAble":true,"planType":4,"zsDuoId":11095755,"planTypeAll":4,"promotionRate":650,"mallRate":10,"optId":10110,"collected":false,"salesTip":"3034","descTxt":"高","servTxt":"高","lgstTxt":"高","isSceneAuth":true,"inBigSale":[10044,10289,10078,10097,10098],"haohuoCouponList":null,"timingUnitVO":null,"brandCouponList":[],"isOnsale":true,"isExtraMissionGoods":false,"unifiedTag":null,"matchType":0},{"mallId":181835268,"mallName":"碧汐美妆","mallLogo":null,"qrCodeImageUrl":null,"merchantType":1,"hasCltCpn":false,"goodsId":97378866472,"goodsName":"无限极植雅牙膏140g正品美白去口臭清新口气去烟渍防蛀牙早晚适用","goodsDesc":"无限极植雅牙膏140g正品美白去口臭清新口气去烟渍防蛀牙早晚适用","goodsImageUrl":"https://t00img.yangkeduo.com/goods/images/2020-03-23/16143a3db72e90328868668337ae5bea.jpeg","goodsThumbnailUrl":"https://t00img.yangkeduo.com/goods/images/2020-03-23/16143a3db72e90328868668337ae5bea.jpeg","minGroupPrice":16500,"categoryId":10110,"categoryName":"洗护","goodsType":1,"hasPddCoupon":null,"hasCoupon":true,"couponMinOrderAmount":11000,"couponDiscount":11000,"couponTotalQuantity":50000,"couponRemainQuantity":45500,"couponStartTime":1594828800,"couponEndTime":1596211199,"mallClientAble":false,"planType":4,"zsDuoId":9232273,"planTypeAll":4,"promotionRate":200,"mallRate":10,"optId":10110,"collected":false,"salesTip":"1.8万","descTxt":"高","servTxt":"高","lgstTxt":"高","isSceneAuth":true,"inBigSale":[10044,10078,10037],"haohuoCouponList":null,"timingUnitVO":null,"brandCouponList":[],"isOnsale":true,"isExtraMissionGoods":false,"unifiedTag":{"tagDTOs":[{"tagSeries":1,"tagId":3,"text":"退货包运费","color":"#FF5706","url":null},{"tagSeries":1,"tagId":24,"text":"极速退款","color":"#FF5706","url":null}],"iconDTOs":[]},"matchType":0},{"mallId":376300767,"mallName":"铱晟文具","mallLogo":null,"qrCodeImageUrl":null,"merchantType":1,"hasCltCpn":false,"goodsId":98495134253,"goodsName":"【考试专用2B橡皮擦】 小学生儿童学习用品 美术橡皮 橡皮擦干净","goodsDesc":"【考试专用2B橡皮擦】 小学生儿童学习用品 美术橡皮 橡皮擦干净","goodsImageUrl":"https://t00img.yangkeduo.com/goods/images/2020-03-25/15194344060d7eefe255a2e005ee3e67.jpeg","goodsThumbnailUrl":"https://t00img.yangkeduo.com/goods/images/2020-03-25/15194344060d7eefe255a2e005ee3e67.jpeg","minGroupPrice":5400,"categoryId":11392,"categoryName":"文化用品","goodsType":1,"hasPddCoupon":null,"hasCoupon":true,"couponMinOrderAmount":2000,"couponDiscount":2000,"couponTotalQuantity":10000,"couponRemainQuantity":6300,"couponStartTime":1595001600,"couponEndTime":1595433599,"mallClientAble":true,"planType":4,"zsDuoId":9991228,"planTypeAll":4,"promotionRate":200,"mallRate":10,"optId":11392,"collected":false,"salesTip":"5.9万","descTxt":"高","servTxt":"高","lgstTxt":"高","isSceneAuth":true,"inBigSale":[10078,10098,10044,21,10311,10289,10277,10296,10138,10294,10000,10119,10096,10064,10037,10140,10127,10323],"haohuoCouponList":null,"timingUnitVO":null,"brandCouponList":[],"isOnsale":true,"isExtraMissionGoods":false,"unifiedTag":{"tagDTOs":[{"tagSeries":1,"tagId":24,"text":"极速退款","color":"#FF5706","url":null}],"iconDTOs":[{"tagSeries":2,"tagId":20013,"text":null,"color":"","url":"https://commimg.pddpic.com/oms_img_ng/2020-07-06/b763cbc5-a35d-4102-a57c-eaaba441c7b8.png"}]},"matchType":0},{"mallId":930707431,"mallName":"并州南食品旗舰店","mallLogo":null,"qrCodeImageUrl":null,"merchantType":3,"hasCltCpn":false,"goodsId":149079204229,"goodsName":"并州南料酒黄酒小瓶装去腥解腻烹调炒菜调味姜葱料酒420ml/瓶批发","goodsDesc":"并州南料酒黄酒小瓶装去腥解腻烹调炒菜调味姜葱料酒420ml/瓶批发","goodsImageUrl":"https://t00img.yangkeduo.com/goods/images/2020-07-07/c54dc0c21cc4002b3fed66d206dada59.jpeg","goodsThumbnailUrl":"https://t00img.yangkeduo.com/goods/images/2020-07-07/c54dc0c21cc4002b3fed66d206dada59.jpeg","minGroupPrice":5900,"categoryId":1,"categoryName":"食品","goodsType":1,"hasPddCoupon":null,"hasCoupon":true,"couponMinOrderAmount":3000,"couponDiscount":3000,"couponTotalQuantity":10000,"couponRemainQuantity":7000,"couponStartTime":1595088000,"couponEndTime":1595519999,"mallClientAble":true,"planType":4,"zsDuoId":9267360,"planTypeAll":4,"promotionRate":200,"mallRate":10,"optId":1,"collected":false,"salesTip":"4854","descTxt":"高","servTxt":"高","lgstTxt":"高","isSceneAuth":true,"inBigSale":[10037,10044,10289,10097,10078,10098],"haohuoCouponList":null,"timingUnitVO":null,"brandCouponList":[],"isOnsale":true,"isExtraMissionGoods":false,"unifiedTag":{"tagDTOs":[{"tagSeries":1,"tagId":3,"text":"退货包运费","color":"#FF5706","url":null},{"tagSeries":1,"tagId":24,"text":"极速退款","color":"#FF5706","url":null}],"iconDTOs":[]},"matchType":0},{"mallId":255100956,"mallName":"涵硕运动户外专营店","mallLogo":null,"qrCodeImageUrl":null,"merchantType":5,"hasCltCpn":false,"goodsId":29183776134,"goodsName":"儿童游泳圈加厚双层腋下1-3-8-16岁成人坐圈宝宝浮力圈小孩泳圈女","goodsDesc":"【Bestway正品保证 90天质量问题换新】\n上市品牌,质量更有保障。游泳圈为双层加厚,为游泳小健将们保驾护航。材质为环保pvc材质,无甲醛用着更放心。","goodsImageUrl":"https://t00img.yangkeduo.com/goods/images/2019-08-08/9a40ebb0010335e32b42788f1a7c1e01.jpeg","goodsThumbnailUrl":"https://t00img.yangkeduo.com/goods/images/2019-08-08/9a40ebb0010335e32b42788f1a7c1e01.jpeg","minGroupPrice":2660,"categoryId":11124,"categoryName":"运动","goodsType":1,"hasPddCoupon":null,"hasCoupon":true,"couponMinOrderAmount":1000,"couponDiscount":1000,"couponTotalQuantity":5000,"couponRemainQuantity":2600,"couponStartTime":1595001600,"couponEndTime":1595606399,"mallClientAble":true,"planType":4,"zsDuoId":1007184,"planTypeAll":4,"promotionRate":200,"mallRate":10,"optId":11124,"collected":false,"salesTip":"7.9万","descTxt":"高","servTxt":"高","lgstTxt":"高","isSceneAuth":false,"inBigSale":[10127,10098,10044,10138,10000,10294,10140,10096,10064,10037,21,10289,10078,10311,10291,10277],"haohuoCouponList":null,"timingUnitVO":null,"brandCouponList":[],"isOnsale":true,"isExtraMissionGoods":false,"unifiedTag":{"tagDTOs":[{"tagSeries":1,"tagId":3,"text":"退货包运费","color":"#FF5706","url":null},{"tagSeries":1,"tagId":24,"text":"极速退款","color":"#FF5706","url":null}],"iconDTOs":[{"tagSeries":2,"tagId":20013,"text":null,"color":"","url":"https://commimg.pddpic.com/oms_img_ng/2020-07-06/b763cbc5-a35d-4102-a57c-eaaba441c7b8.png"}]},"matchType":0},{"mallId":632026222,"mallName":"楷童玩具店","mallLogo":null,"qrCodeImageUrl":null,"merchantType":1,"hasCltCpn":false,"goodsId":149222282196,"goodsName":"儿童玩具车滑翔轨道小汽车回力惯性1女孩2宝宝3岁4多功能男孩益智","goodsDesc":"儿童玩具车滑翔轨道小汽车回力惯性1女孩2宝宝3岁4多功能男孩益智","goodsImageUrl":"https://t00img.yangkeduo.com/goods/images/2020-07-09/d6846e2a91d4c48a869b7b0253117ab3.jpeg","goodsThumbnailUrl":"https://t00img.yangkeduo.com/goods/images/2020-07-09/d6846e2a91d4c48a869b7b0253117ab3.jpeg","minGroupPrice":12900,"categoryId":23010,"categoryName":"母婴","goodsType":1,"hasPddCoupon":null,"hasCoupon":true,"couponMinOrderAmount":7000,"couponDiscount":7000,"couponTotalQuantity":3000,"couponRemainQuantity":900,"couponStartTime":1595088000,"couponEndTime":1595347199,"mallClientAble":true,"planType":4,"zsDuoId":8758556,"planTypeAll":4,"promotionRate":200,"mallRate":10,"optId":23010,"collected":false,"salesTip":"379","descTxt":"高","servTxt":"高","lgstTxt":"高","isSceneAuth":false,"inBigSale":[10098,10078,10037],"haohuoCouponList":null,"timingUnitVO":null,"brandCouponList":[],"isOnsale":true,"isExtraMissionGoods":false,"unifiedTag":{"tagDTOs":[{"tagSeries":1,"tagId":3,"text":"退货包运费","color":"#FF5706","url":null}],"iconDTOs":[]},"matchType":0},{"mallId":954514478,"mallName":"贝心怡云田专卖店","mallLogo":null,"qrCodeImageUrl":null,"merchantType":4,"hasCltCpn":false,"goodsId":57037391095,"goodsName":"贝心怡纯棉洁面巾一次性洗面纸美容纸卷洗面毛巾无菌卸妆棉化妆棉","goodsDesc":"贝心怡纯棉洁面巾一次性洗面纸美容纸卷洗面毛巾无菌卸妆棉化妆棉","goodsImageUrl":"https://t00img.yangkeduo.com/goods/images/2019-10-23/8ac114f66dfe73eb135ed5d0928082e9.jpeg","goodsThumbnailUrl":"https://t00img.yangkeduo.com/goods/images/2019-10-23/8ac114f66dfe73eb135ed5d0928082e9.jpeg","minGroupPrice":7900,"categoryId":10696,"categoryName":"海淘","goodsType":1,"hasPddCoupon":null,"hasCoupon":true,"couponMinOrderAmount":5000,"couponDiscount":5000,"couponTotalQuantity":10000,"couponRemainQuantity":8000,"couponStartTime":1595088000,"couponEndTime":1595260799,"mallClientAble":true,"planType":4,"zsDuoId":8877763,"planTypeAll":4,"promotionRate":200,"mallRate":10,"optId":10696,"collected":false,"salesTip":"1.9万","descTxt":"高","servTxt":"高","lgstTxt":"高","isSceneAuth":true,"inBigSale":[10044,10000,10078,10064],"haohuoCouponList":null,"timingUnitVO":null,"brandCouponList":[],"isOnsale":true,"isExtraMissionGoods":false,"unifiedTag":{"tagDTOs":[{"tagSeries":1,"tagId":3,"text":"退货包运费","color":"#FF5706","url":null},{"tagSeries":1,"tagId":24,"text":"极速退款","color":"#FF5706","url":null}],"iconDTOs":[]},"matchType":0},{"mallId":855731025,"mallName":"岷兴意金归堂专卖店","mallLogo":null,"qrCodeImageUrl":null,"merchantType":4,"hasCltCpn":false,"goodsId":153660710890,"goodsName":"黄芪当归党参正品黄芪茶甘肃中药材滋补气血配枸杞大枣泡水煲汤","goodsDesc":"黄芪当归党参正品黄芪茶甘肃中药材滋补气血配枸杞大枣泡水煲汤","goodsImageUrl":"https://t00img.yangkeduo.com/goods/images/2020-07-16/c064284117bd321631c1b4dd503d66a0.jpeg","goodsThumbnailUrl":"https://t00img.yangkeduo.com/goods/images/2020-07-16/c064284117bd321631c1b4dd503d66a0.jpeg","minGroupPrice":9900,"categoryId":1,"categoryName":"食品","goodsType":1,"hasPddCoupon":null,"hasCoupon":true,"couponMinOrderAmount":7000,"couponDiscount":7000,"couponTotalQuantity":5000,"couponRemainQuantity":3400,"couponStartTime":1595001600,"couponEndTime":1596124799,"mallClientAble":true,"planType":4,"zsDuoId":8979533,"planTypeAll":5,"promotionRate":500,"mallRate":20,"optId":1,"collected":false,"salesTip":"729","descTxt":"高","servTxt":"高","lgstTxt":"高","isSceneAuth":true,"inBigSale":[10078,10098,21],"haohuoCouponList":null,"timingUnitVO":null,"brandCouponList":[],"isOnsale":true,"isExtraMissionGoods":false,"unifiedTag":{"tagDTOs":[{"tagSeries":1,"tagId":3,"text":"退货包运费","color":"#FF5706","url":null},{"tagSeries":1,"tagId":24,"text":"极速退款","color":"#FF5706","url":null}],"iconDTOs":[]},"matchType":0},{"mallId":686573250,"mallName":"梦幻食客三农阳光专卖店","mallLogo":null,"qrCodeImageUrl":null,"merchantType":4,"hasCltCpn":false,"goodsId":104076345424,"goodsName":"【亏本冲量】}新疆骏枣和田大红枣零食补气血免洗即食","goodsDesc":"【亏本冲量】}新疆骏枣和田大红枣零食补气血免洗即食","goodsImageUrl":"https://t00img.yangkeduo.com/goods/images/2020-07-13/9ab8f4217a93f31ed42b4178ab15101b.jpeg","goodsThumbnailUrl":"https://t00img.yangkeduo.com/goods/images/2020-07-13/9ab8f4217a93f31ed42b4178ab15101b.jpeg","minGroupPrice":5900,"categoryId":1,"categoryName":"食品","goodsType":1,"hasPddCoupon":null,"hasCoupon":true,"couponMinOrderAmount":3000,"couponDiscount":3000,"couponTotalQuantity":10000,"couponRemainQuantity":7000,"couponStartTime":1594915200,"couponEndTime":1595865599,"mallClientAble":true,"planType":4,"zsDuoId":9261189,"planTypeAll":4,"promotionRate":200,"mallRate":10,"optId":1,"collected":false,"salesTip":"2.5万","descTxt":"高","servTxt":"高","lgstTxt":"高","isSceneAuth":true,"inBigSale":[10037,10289,10000,10098,10078,10044,10097],"haohuoCouponList":null,"timingUnitVO":null,"brandCouponList":[],"isOnsale":true,"isExtraMissionGoods":false,"unifiedTag":{"tagDTOs":[{"tagSeries":1,"tagId":3,"text":"退货包运费","color":"#FF5706","url":null}],"iconDTOs":[]},"matchType":0},{"mallId":414125144,"mallName":"橄榄时光官方旗舰店","mallLogo":null,"qrCodeImageUrl":null,"merchantType":3,"hasCltCpn":false,"goodsId":145518868253,"goodsName":"橄榄时光小鸭腿香辣口味小香腿旅游小酌零食乡巴佬独特风味热卖款","goodsDesc":"橄榄时光小鸭腿香辣口味小香腿旅游小酌零食乡巴佬独特风味热卖款","goodsImageUrl":"https://t00img.yangkeduo.com/goods/images/2020-06-30/31cad78045994dab066e57cad2f23a63.jpeg","goodsThumbnailUrl":"https://t00img.yangkeduo.com/goods/images/2020-06-30/31cad78045994dab066e57cad2f23a63.jpeg","minGroupPrice":7900,"categoryId":1,"categoryName":"食品","goodsType":1,"hasPddCoupon":null,"hasCoupon":true,"couponMinOrderAmount":4000,"couponDiscount":4000,"couponTotalQuantity":3500,"couponRemainQuantity":2900,"couponStartTime":1595088000,"couponEndTime":1595606399,"mallClientAble":false,"planType":4,"zsDuoId":10601935,"planTypeAll":4,"promotionRate":200,"mallRate":100,"optId":1,"collected":false,"salesTip":"4183","descTxt":"高","servTxt":"高","lgstTxt":"高","isSceneAuth":true,"inBigSale":[10098,10044,10097,10289,10037,10078,10000],"haohuoCouponList":null,"timingUnitVO":null,"brandCouponList":[],"isOnsale":true,"isExtraMissionGoods":false,"unifiedTag":{"tagDTOs":[{"tagSeries":1,"tagId":3,"text":"退货包运费","color":"#FF5706","url":null},{"tagSeries":1,"tagId":24,"text":"极速退款","color":"#FF5706","url":null}],"iconDTOs":[]},"matchType":0},{"mallId":432422896,"mallName":"裕祥家居生活官方旗舰店","mallLogo":null,"qrCodeImageUrl":null,"merchantType":3,"hasCltCpn":false,"goodsId":142925632485,"goodsName":"菜刀厨房刀具砍骨刀切菜刀德国工艺锋利不锈钢厨师刀家用菜刀套装","goodsDesc":"菜刀厨房刀具砍骨刀切菜刀德国工艺锋利不锈钢厨师刀家用菜刀套装","goodsImageUrl":"https://t00img.yangkeduo.com/goods/images/2020-07-12/147469f7354282b1a14de03c3fa6c54c.jpeg","goodsThumbnailUrl":"https://t00img.yangkeduo.com/goods/images/2020-07-12/147469f7354282b1a14de03c3fa6c54c.jpeg","minGroupPrice":17800,"categoryId":11295,"categoryName":"厨房/烹饪用具","goodsType":1,"hasPddCoupon":null,"hasCoupon":true,"couponMinOrderAmount":14000,"couponDiscount":14000,"couponTotalQuantity":3000,"couponRemainQuantity":2900,"couponStartTime":1595174400,"couponEndTime":1595519999,"mallClientAble":false,"planType":4,"zsDuoId":9243510,"planTypeAll":4,"promotionRate":200,"mallRate":10,"optId":11295,"collected":false,"salesTip":"2066","descTxt":"高","servTxt":"高","lgstTxt":"高","isSceneAuth":true,"inBigSale":[10311,10277,10294,10127,10298,10296,10078,10096,10138,10140,10044,10289,10097,10098,10037,20],"haohuoCouponList":null,"timingUnitVO":null,"brandCouponList":[],"isOnsale":true,"isExtraMissionGoods":false,"unifiedTag":{"tagDTOs":[{"tagSeries":2,"tagId":10001,"text":"新品","color":"#E02E24","url":null},{"tagSeries":1,"tagId":3,"text":"退货包运费","color":"#FF5706","url":null},{"tagSeries":1,"tagId":24,"text":"极速退款","color":"#FF5706","url":null}],"iconDTOs":[{"tagSeries":2,"tagId":20013,"text":null,"color":"","url":"https://commimg.pddpic.com/oms_img_ng/2020-07-06/b763cbc5-a35d-4102-a57c-eaaba441c7b8.png"}]},"matchType":0},{"mallId":989049455,"mallName":"明翔食品保健专营店","mallLogo":null,"qrCodeImageUrl":null,"merchantType":5,"hasCltCpn":false,"goodsId":135404582556,"goodsName":"黄金蛋黄酥点心饼干甜品糯米糕点吃月饼网红休闲小零食糕点类早餐","goodsDesc":"黄金蛋黄酥点心饼干甜品糯米糕点吃月饼网红休闲小零食糕点类早餐","goodsImageUrl":"https://t00img.yangkeduo.com/goods/images/2020-06-15/d3923a1ca76ba5efcb3d3c0d3a9ba831.jpeg","goodsThumbnailUrl":"https://t00img.yangkeduo.com/goods/images/2020-06-15/d3923a1ca76ba5efcb3d3c0d3a9ba831.jpeg","minGroupPrice":14990,"categoryId":1,"categoryName":"食品","goodsType":1,"hasPddCoupon":null,"hasCoupon":true,"couponMinOrderAmount":11000,"couponDiscount":11000,"couponTotalQuantity":10000,"couponRemainQuantity":7000,"couponStartTime":1595088000,"couponEndTime":1595433599,"mallClientAble":true,"planType":4,"zsDuoId":9943282,"planTypeAll":4,"promotionRate":200,"mallRate":10,"optId":1,"collected":false,"salesTip":"1.9万","descTxt":"高","servTxt":"高","lgstTxt":"高","isSceneAuth":true,"inBigSale":[10296,10096,10294,10000,10140,10114,10142,10286,10138,10127,10037,10311,10044,10277,10078,10097,10304,10289,10306,10098],"haohuoCouponList":null,"timingUnitVO":null,"brandCouponList":[],"isOnsale":true,"isExtraMissionGoods":false,"unifiedTag":{"tagDTOs":[{"tagSeries":1,"tagId":24,"text":"极速退款","color":"#FF5706","url":null}],"iconDTOs":[{"tagSeries":2,"tagId":20013,"text":null,"color":"","url":"https://commimg.pddpic.com/oms_img_ng/2020-07-06/b763cbc5-a35d-4102-a57c-eaaba441c7b8.png"}]},"matchType":0},{"mallId":860021,"mallName":"锐驰眼镜店","mallLogo":null,"qrCodeImageUrl":null,"merchantType":1,"hasCltCpn":false,"goodsId":142448679936,"goodsName":"防走光扣纽扣免缝暗扣隐形ins风胸针饰品小香风可爱衬衫按扣扣子","goodsDesc":"防走光扣纽扣免缝暗扣隐形ins风胸针饰品小香风可爱衬衫按扣扣子","goodsImageUrl":"https://t00img.yangkeduo.com/goods/images/2020-07-18/ac3f12cdd6449292b0e8d48760473a55.jpeg","goodsThumbnailUrl":"https://t00img.yangkeduo.com/goods/images/2020-07-18/ac3f12cdd6449292b0e8d48760473a55.jpeg","minGroupPrice":6900,"categoryId":10696,"categoryName":"海淘","goodsType":1,"hasPddCoupon":null,"hasCoupon":true,"couponMinOrderAmount":3000,"couponDiscount":3000,"couponTotalQuantity":2000,"couponRemainQuantity":700,"couponStartTime":1595088000,"couponEndTime":1595260799,"mallClientAble":true,"planType":4,"zsDuoId":9146866,"planTypeAll":4,"promotionRate":300,"mallRate":50,"optId":10696,"collected":false,"salesTip":"8317","descTxt":"高","servTxt":"高","lgstTxt":"高","isSceneAuth":true,"inBigSale":[10311,10140,10044,10037,10078,10298,10277,10096,10289,10097,10138,10296,10127,10098,10294],"haohuoCouponList":null,"timingUnitVO":null,"brandCouponList":[],"isOnsale":true,"isExtraMissionGoods":false,"unifiedTag":{"tagDTOs":[],"iconDTOs":[{"tagSeries":2,"tagId":20013,"text":null,"color":"","url":"https://commimg.pddpic.com/oms_img_ng/2020-07-06/b763cbc5-a35d-4102-a57c-eaaba441c7b8.png"}]},"matchType":0},{"mallId":458514645,"mallName":"LMIS家居生活旗舰店","mallLogo":null,"qrCodeImageUrl":null,"merchantType":3,"hasCltCpn":false,"goodsId":124719007991,"goodsName":"德国钼钒钢菜刀具全套装组合厨房家用斩砍骨切肉片切菜不锈钢锋利","goodsDesc":"德国钼钒钢菜刀具全套装组合厨房家用斩砍骨切肉片切菜不锈钢锋利","goodsImageUrl":"https://t00img.yangkeduo.com/goods/images/2020-07-04/68ab343ccbbfc257ecc7b7fcc0bf32d4.jpeg","goodsThumbnailUrl":"https://t00img.yangkeduo.com/goods/images/2020-07-04/68ab343ccbbfc257ecc7b7fcc0bf32d4.jpeg","minGroupPrice":29990,"categoryId":11295,"categoryName":"厨房/烹饪用具","goodsType":1,"hasPddCoupon":null,"hasCoupon":true,"couponMinOrderAmount":23000,"couponDiscount":23000,"couponTotalQuantity":3000,"couponRemainQuantity":2200,"couponStartTime":1595174400,"couponEndTime":1595519999,"mallClientAble":true,"planType":4,"zsDuoId":8679399,"planTypeAll":4,"promotionRate":400,"mallRate":1,"optId":11295,"collected":false,"salesTip":"3377","descTxt":"高","servTxt":"高","lgstTxt":"高","isSceneAuth":true,"inBigSale":[10138,10127,10037,10140,21,10096,10296,10078,10098,10298,10311,10294,10277,10044],"haohuoCouponList":null,"timingUnitVO":null,"brandCouponList":[],"isOnsale":true,"isExtraMissionGoods":false,"unifiedTag":{"tagDTOs":[{"tagSeries":1,"tagId":3,"text":"退货包运费","color":"#FF5706","url":null},{"tagSeries":1,"tagId":24,"text":"极速退款","color":"#FF5706","url":null}],"iconDTOs":[{"tagSeries":2,"tagId":20013,"text":null,"color":"","url":"https://commimg.pddpic.com/oms_img_ng/2020-07-06/b763cbc5-a35d-4102-a57c-eaaba441c7b8.png"}]},"matchType":0},{"mallId":265634395,"mallName":"半升岛食品旗舰店","mallLogo":null,"qrCodeImageUrl":null,"merchantType":3,"hasCltCpn":false,"goodsId":7178238522,"goodsName":"手撕素牛排素肉零食豆腐皮特产小吃食品麻辣油炸素食素牛肉豆腐干","goodsDesc":"手撕素牛排素肉零食豆腐皮特产小吃食品麻辣油炸素食素牛肉豆腐干","goodsImageUrl":"https://t00img.yangkeduo.com/goods/images/2020-05-25/47dcbe7748c513417ad2709b9a4971f9.jpeg","goodsThumbnailUrl":"https://t00img.yangkeduo.com/goods/images/2020-05-25/47dcbe7748c513417ad2709b9a4971f9.jpeg","minGroupPrice":6900,"categoryId":1,"categoryName":"食品","goodsType":1,"hasPddCoupon":null,"hasCoupon":true,"couponMinOrderAmount":2000,"couponDiscount":2000,"couponTotalQuantity":50000,"couponRemainQuantity":36000,"couponStartTime":1594310400,"couponEndTime":1598889599,"mallClientAble":true,"planType":2,"zsDuoId":0,"planTypeAll":0,"promotionRate":200,"mallRate":20,"optId":1,"collected":false,"salesTip":"10万+","descTxt":"高","servTxt":"高","lgstTxt":"高","isSceneAuth":false,"inBigSale":[10140,10078,10138,10114,10037,10311,10277,10098,10142,10306,10000,10127,10296,21,10096,10304,10044,10294,10286],"haohuoCouponList":null,"timingUnitVO":null,"brandCouponList":[],"isOnsale":true,"isExtraMissionGoods":false,"unifiedTag":{"tagDTOs":[{"tagSeries":1,"tagId":24,"text":"极速退款","color":"#FF5706","url":null}],"iconDTOs":[{"tagSeries":2,"tagId":20013,"text":null,"color":"","url":"https://commimg.pddpic.com/oms_img_ng/2020-07-06/b763cbc5-a35d-4102-a57c-eaaba441c7b8.png"}]},"matchType":0},{"mallId":335165765,"mallName":"茗熙阁食品坊","mallLogo":null,"qrCodeImageUrl":null,"merchantType":6,"hasCltCpn":false,"goodsId":100297791982,"goodsName":"菊花枸杞决明子茶金银花茶去火熬夜恢复茶男女花茶组合茶包养生茶","goodsDesc":"菊花枸杞决明子茶金银花茶去火熬夜恢复茶男女花茶组合茶包养生茶","goodsImageUrl":"https://t00img.yangkeduo.com/goods/images/2020-05-07/076abee618b85c6c7d4fb09866fffbcf.jpeg","goodsThumbnailUrl":"https://t00img.yangkeduo.com/goods/images/2020-05-07/076abee618b85c6c7d4fb09866fffbcf.jpeg","minGroupPrice":10800,"categoryId":11906,"categoryName":"茶","goodsType":1,"hasPddCoupon":null,"hasCoupon":true,"couponMinOrderAmount":5000,"couponDiscount":5000,"couponTotalQuantity":50000,"couponRemainQuantity":46000,"couponStartTime":1594828800,"couponEndTime":1596211199,"mallClientAble":true,"planType":2,"zsDuoId":0,"planTypeAll":4,"promotionRate":200,"mallRate":10,"optId":11906,"collected":false,"salesTip":"3334","descTxt":"高","servTxt":"高","lgstTxt":"高","isSceneAuth":true,"inBigSale":[10127,10037,10306,10064,10140,10286,10304,10096,10294,10138,10078,10000,10098,10277,10311,10044,10114,10296],"haohuoCouponList":null,"timingUnitVO":null,"brandCouponList":[],"isOnsale":true,"isExtraMissionGoods":false,"unifiedTag":{"tagDTOs":[{"tagSeries":1,"tagId":3,"text":"退货包运费","color":"#FF5706","url":null},{"tagSeries":1,"tagId":24,"text":"极速退款","color":"#FF5706","url":null}],"iconDTOs":[{"tagSeries":2,"tagId":20013,"text":null,"color":"","url":"https://commimg.pddpic.com/oms_img_ng/2020-07-06/b763cbc5-a35d-4102-a57c-eaaba441c7b8.png"}]},"matchType":0},{"mallId":148108697,"mallName":"春大哥食品旗舰店","mallLogo":null,"qrCodeImageUrl":null,"merchantType":3,"hasCltCpn":false,"goodsId":148541832449,"goodsName":"网红薯片零食小吃大礼包好吃便宜的儿童学生休闲小零食整箱批发","goodsDesc":"网红薯片零食小吃大礼包好吃便宜的儿童学生休闲小零食整箱批发","goodsImageUrl":"https://t00img.yangkeduo.com/goods/images/2020-07-06/0e93b1eccbe93e4e8626f538d60fa829.jpeg","goodsThumbnailUrl":"https://t00img.yangkeduo.com/goods/images/2020-07-06/0e93b1eccbe93e4e8626f538d60fa829.jpeg","minGroupPrice":4900,"categoryId":1,"categoryName":"食品","goodsType":1,"hasPddCoupon":null,"hasCoupon":true,"couponMinOrderAmount":2000,"couponDiscount":2000,"couponTotalQuantity":2000,"couponRemainQuantity":400,"couponStartTime":1595088000,"couponEndTime":1595347199,"mallClientAble":true,"planType":4,"zsDuoId":8972470,"planTypeAll":4,"promotionRate":210,"mallRate":10,"optId":1,"collected":false,"salesTip":"2185","descTxt":"高","servTxt":"高","lgstTxt":"高","isSceneAuth":true,"inBigSale":[10098,10142,10114,10286,10277,10096,10294,10306,10138,10304,10140,10296,10311,10044,10127,10078],"haohuoCouponList":null,"timingUnitVO":null,"brandCouponList":[],"isOnsale":true,"isExtraMissionGoods":false,"unifiedTag":{"tagDTOs":[{"tagSeries":1,"tagId":3,"text":"退货包运费","color":"#FF5706","url":null}],"iconDTOs":[{"tagSeries":2,"tagId":20013,"text":null,"color":"","url":"https://commimg.pddpic.com/oms_img_ng/2020-07-06/b763cbc5-a35d-4102-a57c-eaaba441c7b8.png"}]},"matchType":0},{"mallId":440273660,"mallName":"SUSCONG官方旗舰店","mallLogo":null,"qrCodeImageUrl":null,"merchantType":3,"hasCltCpn":false,"goodsId":135519797139,"goodsName":"BDAC驱蚊喷雾宝宝驱虫液户外防蚊虫叮咬神器驱蚊止痒液体防蚊喷雾","goodsDesc":"BDAC驱蚊喷雾宝宝驱虫液户外防蚊虫叮咬神器驱蚊止痒液体防蚊喷雾","goodsImageUrl":"https://t00img.yangkeduo.com/goods/images/2020-07-20/2d28ce564e241ae2d5ff083bf0ad356e.jpeg","goodsThumbnailUrl":"https://t00img.yangkeduo.com/goods/images/2020-07-20/2d28ce564e241ae2d5ff083bf0ad356e.jpeg","minGroupPrice":15900,"categoryId":10110,"categoryName":"洗护","goodsType":1,"hasPddCoupon":null,"hasCoupon":true,"couponMinOrderAmount":5000,"couponDiscount":5000,"couponTotalQuantity":50000,"couponRemainQuantity":46000,"couponStartTime":1595001600,"couponEndTime":1595433599,"mallClientAble":true,"planType":4,"zsDuoId":8779287,"planTypeAll":4,"promotionRate":600,"mallRate":10,"optId":10110,"collected":false,"salesTip":"7950","descTxt":"高","servTxt":"高","lgstTxt":"高","isSceneAuth":true,"inBigSale":[10289,10097,10000,10044,10037,10098,10078],"haohuoCouponList":null,"timingUnitVO":null,"brandCouponList":[],"isOnsale":true,"isExtraMissionGoods":false,"unifiedTag":null,"matchType":0},{"mallId":870866743,"mallName":"阿巴兔官方旗舰店","mallLogo":null,"qrCodeImageUrl":null,"merchantType":3,"hasCltCpn":false,"goodsId":65260604218,"goodsName":"青蛙王子儿童牙膏换牙期小童3-6-12岁以上防蛀牙膏牙刷套装中大童","goodsDesc":"青蛙王子儿童牙膏换牙期小童3-6-12岁以上防蛀牙膏牙刷套装中大童","goodsImageUrl":"https://t00img.yangkeduo.com/goods/images/2020-07-07/fdfc01d978f8e4d17f16a141fd188107.jpeg","goodsThumbnailUrl":"https://t00img.yangkeduo.com/goods/images/2020-07-07/fdfc01d978f8e4d17f16a141fd188107.jpeg","minGroupPrice":6900,"categoryId":10696,"categoryName":"海淘","goodsType":1,"hasPddCoupon":null,"hasCoupon":true,"couponMinOrderAmount":2000,"couponDiscount":2000,"couponTotalQuantity":8000,"couponRemainQuantity":2000,"couponStartTime":1595001600,"couponEndTime":1595260799,"mallClientAble":true,"planType":4,"zsDuoId":2026587,"planTypeAll":5,"promotionRate":200,"mallRate":10,"optId":10696,"collected":false,"salesTip":"6.2万","descTxt":"高","servTxt":"高","lgstTxt":"高","isSceneAuth":true,"inBigSale":[10000,10292,10097,21,10078,10289,31,10064,10318,10098,24,10316,10044,10037],"haohuoCouponList":null,"timingUnitVO":null,"brandCouponList":[],"isOnsale":true,"isExtraMissionGoods":false,"unifiedTag":{"tagDTOs":[{"tagSeries":1,"tagId":3,"text":"退货包运费","color":"#FF5706","url":null},{"tagSeries":1,"tagId":36,"text":"正品险","color":"#FF5706","url":null}],"iconDTOs":[]},"matchType":0},{"mallId":774576,"mallName":"依居家官方旗舰店","mallLogo":null,"qrCodeImageUrl":null,"merchantType":3,"hasCltCpn":false,"goodsId":154642819931,"goodsName":"依居家夏季家居浴室洗澡加厚防滑地板拖鞋室内外男女通用情侣拖鞋","goodsDesc":"依居家夏季家居浴室洗澡加厚防滑地板拖鞋室内外男女通用情侣拖鞋","goodsImageUrl":"https://t00img.yangkeduo.com/goods/images/2020-07-18/325a93b6004e3dfcfcbe763d812d54d6.jpeg","goodsThumbnailUrl":"https://t00img.yangkeduo.com/goods/images/2020-07-18/325a93b6004e3dfcfcbe763d812d54d6.jpeg","minGroupPrice":6900,"categoryId":15,"categoryName":"百货","goodsType":1,"hasPddCoupon":null,"hasCoupon":true,"couponMinOrderAmount":2000,"couponDiscount":2000,"couponTotalQuantity":50000,"couponRemainQuantity":42500,"couponStartTime":1595001600,"couponEndTime":1595519999,"mallClientAble":true,"planType":4,"zsDuoId":9356923,"planTypeAll":4,"promotionRate":200,"mallRate":10,"optId":15,"collected":false,"salesTip":"940","descTxt":"高","servTxt":"高","lgstTxt":"高","isSceneAuth":true,"inBigSale":[10078,31,10098,24],"haohuoCouponList":null,"timingUnitVO":null,"brandCouponList":[],"isOnsale":true,"isExtraMissionGoods":false,"unifiedTag":{"tagDTOs":[{"tagSeries":1,"tagId":3,"text":"退货包运费","color":"#FF5706","url":null},{"tagSeries":1,"tagId":24,"text":"极速退款","color":"#FF5706","url":null}],"iconDTOs":[]},"matchType":0},{"mallId":21985,"mallName":"语萱家居","mallLogo":null,"qrCodeImageUrl":null,"merchantType":6,"hasCltCpn":false,"goodsId":6346287231,"goodsName":"黑色磨砂中性笔0.5 0.38子弹头全针管碳素笔水性笔文化办公用品","goodsDesc":"主要产品分为0.5mm子弹头和0.38全针管中性笔和笔芯,买就送笔芯,笔芯有黑,蓝,红3种颜色供亲选择,【包装为简易散装,质量是一样的,亲们可以放心购买!】---------注:不同的套餐有不同的优惠哦,有不懂的亲可以联系客服。","goodsImageUrl":"https://t00img.yangkeduo.com/goods/images/2019-03-30/dbe8233758d1878c37ea72f4942058a8.jpeg","goodsThumbnailUrl":"https://t00img.yangkeduo.com/goods/images/2019-03-30/dbe8233758d1878c37ea72f4942058a8.jpeg","minGroupPrice":2990,"categoryId":11392,"categoryName":"文化用品","goodsType":1,"hasPddCoupon":null,"hasCoupon":true,"couponMinOrderAmount":2000,"couponDiscount":2000,"couponTotalQuantity":2000,"couponRemainQuantity":1000,"couponStartTime":1595174400,"couponEndTime":1595606399,"mallClientAble":true,"planType":4,"zsDuoId":8394539,"planTypeAll":4,"promotionRate":310,"mallRate":100,"optId":11392,"collected":false,"salesTip":"10万+","descTxt":"高","servTxt":"高","lgstTxt":"高","isSceneAuth":true,"inBigSale":[10296,10078,21,10311,10294,10000,10289,10119,10037,10044,10098,10323],"haohuoCouponList":null,"timingUnitVO":null,"brandCouponList":[],"isOnsale":true,"isExtraMissionGoods":false,"unifiedTag":{"tagDTOs":[{"tagSeries":1,"tagId":24,"text":"极速退款","color":"#FF5706","url":null}],"iconDTOs":[{"tagSeries":2,"tagId":20013,"text":null,"color":"","url":"https://commimg.pddpic.com/oms_img_ng/2020-07-06/b763cbc5-a35d-4102-a57c-eaaba441c7b8.png"}]},"matchType":0},{"mallId":150142884,"mallName":"炳昱旗舰店","mallLogo":null,"qrCodeImageUrl":null,"merchantType":3,"hasCltCpn":false,"goodsId":150923678434,"goodsName":"黑框眼镜女防紫外线太阳镜男韩版墨镜网红同款防强光大脸显瘦眼睛","goodsDesc":"黑框眼镜女防紫外线太阳镜男韩版墨镜网红同款防强光大脸显瘦眼睛","goodsImageUrl":"https://t00img.yangkeduo.com/goods/images/2020-07-11/7d909d4940c3f888169977e28b11e2dd.jpeg","goodsThumbnailUrl":"https://t00img.yangkeduo.com/goods/images/2020-07-11/7d909d4940c3f888169977e28b11e2dd.jpeg","minGroupPrice":3900,"categoryId":1281,"categoryName":"鞋包","goodsType":1,"hasPddCoupon":null,"hasCoupon":true,"couponMinOrderAmount":2000,"couponDiscount":2000,"couponTotalQuantity":1000,"couponRemainQuantity":800,"couponStartTime":1595174400,"couponEndTime":1595433599,"mallClientAble":true,"planType":4,"zsDuoId":10243203,"planTypeAll":4,"promotionRate":230,"mallRate":20,"optId":1281,"collected":false,"salesTip":"2126","descTxt":"高","servTxt":"高","lgstTxt":"高","isSceneAuth":true,"inBigSale":[10098,20,10078,10037,10044],"haohuoCouponList":null,"timingUnitVO":null,"brandCouponList":[],"isOnsale":true,"isExtraMissionGoods":false,"unifiedTag":{"tagDTOs":[{"tagSeries":2,"tagId":10001,"text":"新品","color":"#E02E24","url":null},{"tagSeries":1,"tagId":3,"text":"退货包运费","color":"#FF5706","url":null},{"tagSeries":1,"tagId":24,"text":"极速退款","color":"#FF5706","url":null}],"iconDTOs":[]},"matchType":0},{"mallId":478648055,"mallName":"乐顺蔬菜","mallLogo":null,"qrCodeImageUrl":null,"merchantType":6,"hasCltCpn":false,"goodsId":124861734117,"goodsName":"真贝贝南瓜板栗味日本进口老南瓜迷你小南瓜香甜粉糯新鲜采摘包邮","goodsDesc":"真贝贝南瓜板栗味日本进口老南瓜迷你小南瓜香甜粉糯新鲜采摘包邮","goodsImageUrl":"https://t00img.yangkeduo.com/goods/images/2020-05-20/6460bb2d9e618cf9b7caca89f3e649d5.jpeg","goodsThumbnailUrl":"https://t00img.yangkeduo.com/goods/images/2020-05-20/6460bb2d9e618cf9b7caca89f3e649d5.jpeg","minGroupPrice":9860,"categoryId":10696,"categoryName":"海淘","goodsType":1,"hasPddCoupon":null,"hasCoupon":true,"couponMinOrderAmount":4000,"couponDiscount":4000,"couponTotalQuantity":50000,"couponRemainQuantity":46000,"couponStartTime":1595174400,"couponEndTime":1595692799,"mallClientAble":false,"planType":2,"zsDuoId":0,"planTypeAll":0,"promotionRate":350,"mallRate":100,"optId":10696,"collected":false,"salesTip":"3085","descTxt":"高","servTxt":"高","lgstTxt":"高","isSceneAuth":true,"inBigSale":[10098,10044,10037,10078,10097,10000,10064],"haohuoCouponList":null,"timingUnitVO":null,"brandCouponList":[],"isOnsale":true,"isExtraMissionGoods":false,"unifiedTag":{"tagDTOs":[{"tagSeries":1,"tagId":24,"text":"极速退款","color":"#FF5706","url":null}],"iconDTOs":[]},"matchType":0}],"recommendGoodsList":[],"recReasonGoodsList":[],"isSimilarEnable":false,"searchProperty":null}}